[
  {
    "productId": 231299,
    "name": "First Partner Pack (Galar)",
    "cleanName": "First Partner Pack Galar",
    "imageUrl": "https://tcgplayer-cdn.tcgplayer.com/product/231299_200w.jpg",
    "categoryId": 3,
    "groupId": 2776,
    "url": "https://www.tcgplayer.com/product/231299/pokemon-first-partner-pack-first-partner-pack-galar",
    "modifiedOn": "2021-03-05T05:03:21.527",
    "imageCount": 1,
    "presaleInfo": {
      "isPresale": false,
      "releasedOn": "2021-03-05T00:00:00",
      "note": null
    },
    "extendedData": [
      {
        "name": "CardText",
        "displayName": "Card Text",
        "value": "Includes three oversize promo cards featuring the first partner Pokémon of the\r\nGalar region—Grookey, Scorbunny, and Sobble—plus two regular Pokémon TCG boosters."
      },
      {
        "name": "UPC",
        "displayName": "UPC",
        "value": "0820650809613"
      }
    ],
    "prices": [
      {
        "subTypeName": "Normal",
        "lowPrice": 16.01,
        "midPrice": 25,
        "highPrice": 27.92,
        "marketPrice": 15.65,
        "directLowPrice": null
      }
    ]
  },
  {
    "productId": 231300,
    "name": "First Partner Pack (Alola)",
    "cleanName": "First Partner Pack Alola",
    "imageUrl": "https://tcgplayer-cdn.tcgplayer.com/product/231300_200w.jpg",
    "categoryId": 3,
    "groupId": 2776,
    "url": "https://www.tcgplayer.com/product/231300/pokemon-first-partner-pack-first-partner-pack-alola",
    "modifiedOn": "2021-04-02T04:03:07.323",
    "imageCount": 1,
    "presaleInfo": {
      "isPresale": false,
      "releasedOn": "2021-03-05T00:00:00",
      "note": null
    },
    "extendedData": [
      {
        "name": "CardText",
        "displayName": "Card Text",
        "value": "Includes three oversize promo cards featuring the first partner Pokémon of the Alola region—Rowlet, Litten, and Popplio—plus two regular Pokémon TCG boosters."
      },
      {
        "name": "UPC",
        "displayName": "UPC",
        "value": "0820650819629"
      }
    ],
    "prices": [
      {
        "subTypeName": "Normal",
        "lowPrice": 14.5,
        "midPrice": 18.5,
        "highPrice": 25,
        "marketPrice": 15.85,
        "directLowPrice": null
      }
    ]
  },
  {
    "productId": 231301,
    "name": "First Partner Pack (Kalos)",
    "cleanName": "First Partner Pack Kalos",
    "imageUrl": "https://tcgplayer-cdn.tcgplayer.com/product/231301_200w.jpg",
    "categoryId": 3,
    "groupId": 2776,
    "url": "https://www.tcgplayer.com/product/231301/pokemon-first-partner-pack-first-partner-pack-kalos",
    "modifiedOn": "2021-05-07T04:03:11.703",
    "imageCount": 1,
    "presaleInfo": {
      "isPresale": false,
      "releasedOn": "2021-03-05T00:00:00",
      "note": null
    },
    "extendedData": [
      {
        "name": "CardText",
        "displayName": "Card Text",
        "value": "Includes three oversize promo cards featuring the first partner Pokémon of the Kalos region—Chespin, Fennekin, and Froakie—plus two regular Pokémon TCG boosters."
      },
      {
        "name": "UPC",
        "displayName": "UPC",
        "value": "0820650819636"
      }
    ],
    "prices": [
      {
        "subTypeName": "Normal",
        "lowPrice": 14.33,
        "midPrice": 15,
        "highPrice": 20,
        "marketPrice": 14.17,
        "directLowPrice": null
      }
    ]
  },
  {
    "productId": 231302,
    "name": "First Partner Pack (Unova)",
    "cleanName": "First Partner Pack Unova",
    "imageUrl": "https://tcgplayer-cdn.tcgplayer.com/product/231302_200w.jpg",
    "categoryId": 3,
    "groupId": 2776,
    "url": "https://www.tcgplayer.com/product/231302/pokemon-first-partner-pack-first-partner-pack-unova",
    "modifiedOn": "2021-06-04T04:03:36.873",
    "imageCount": 1,
    "presaleInfo": {
      "isPresale": false,
      "releasedOn": "2021-03-05T00:00:00",
      "note": null
    },
    "extendedData": [
      {
        "name": "CardText",
        "displayName": "Card Text",
        "value": "Includes three oversize promo cards featuring the first partner Pokémon of the Unova region—Snivy, Tepig, and Oshawott—plus two regular Pokémon TCG boosters."
      },
      {
        "name": "UPC",
        "displayName": "UPC",
        "value": "0820650819643"
      }
    ],
    "prices": [
      {
        "subTypeName": "Normal",
        "lowPrice": 10.93,
        "midPrice": 14.99,
        "highPrice": 24.95,
        "marketPrice": 13.34,
        "directLowPrice": null
      }
    ]
  },
  {
    "productId": 231303,
    "name": "First Partner Pack (Sinnoh)",
    "cleanName": "First Partner Pack Sinnoh",
    "imageUrl": "https://tcgplayer-cdn.tcgplayer.com/product/231303_200w.jpg",
    "categoryId": 3,
    "groupId": 2776,
    "url": "https://www.tcgplayer.com/product/231303/pokemon-first-partner-pack-first-partner-pack-sinnoh",
    "modifiedOn": "2021-07-09T04:03:08.203",
    "imageCount": 1,
    "presaleInfo": {
      "isPresale": false,
      "releasedOn": "2021-03-05T00:00:00",
      "note": null
    },
    "extendedData": [
      {
        "name": "CardText",
        "displayName": "Card Text",
        "value": "Includes three oversize promo cards featuring the first partner Pokémon of the Sinnoh region—Turtwig, Chimchar, and Piplup—plus two regular Pokémon TCG boosters."
      },
      {
        "name": "UPC",
        "displayName": "UPC",
        "value": "0820650819650"
      }
    ],
    "prices": [
      {
        "subTypeName": "Normal",
        "lowPrice": 14.99,
        "midPrice": 17.99,
        "highPrice": 30.99,
        "marketPrice": 13,
        "directLowPrice": null
      }
    ]
  },
  {
    "productId": 231304,
    "name": "First Partner Pack (Hoenn)",
    "cleanName": "First Partner Pack Hoenn",
    "imageUrl": "https://tcgplayer-cdn.tcgplayer.com/product/231304_200w.jpg",
    "categoryId": 3,
    "groupId": 2776,
    "url": "https://www.tcgplayer.com/product/231304/pokemon-first-partner-pack-first-partner-pack-hoenn",
    "modifiedOn": "2021-08-12T04:03:07.89",
    "imageCount": 1,
    "presaleInfo": {
      "isPresale": false,
      "releasedOn": "2021-03-05T00:00:00",
      "note": null
    },
    "extendedData": [
      {
        "name": "CardText",
        "displayName": "Card Text",
        "value": "Includes three oversize promo cards featuring the first partner Pokémon of the Hoenn region—Treecko, Torchic, and Mudkip—plus two regular Pokémon TCG boosters."
      },
      {
        "name": "UPC",
        "displayName": "UPC",
        "value": "0820650819674"
      }
    ],
    "prices": [
      {
        "subTypeName": "Normal",
        "lowPrice": 14.99,
        "midPrice": 20,
        "highPrice": 25,
        "marketPrice": 13.89,
        "directLowPrice": null
      }
    ]
  },
  {
    "productId": 231305,
    "name": "First Partner Pack (Johto)",
    "cleanName": "First Partner Pack Johto",
    "imageUrl": "https://tcgplayer-cdn.tcgplayer.com/product/231305_200w.jpg",
    "categoryId": 3,
    "groupId": 2776,
    "url": "https://www.tcgplayer.com/product/231305/pokemon-first-partner-pack-first-partner-pack-johto",
    "modifiedOn": "2021-09-10T04:03:07.857",
    "imageCount": 1,
    "presaleInfo": {
      "isPresale": false,
      "releasedOn": "2021-03-05T00:00:00",
      "note": null
    },
    "extendedData": [
      {
        "name": "CardText",
        "displayName": "Card Text",
        "value": "Includes three oversize promo cards featuring the first partner Pokémon of the Johto region—Chikorita, Cyndaquil, and Totodile—plus two regular Pokémon TCG boosters."
      },
      {
        "name": "UPC",
        "displayName": "UPC",
        "value": "0820650819674"
      }
    ],
    "prices": [
      {
        "subTypeName": "Normal",
        "lowPrice": 37.11,
        "midPrice": 38.49,
        "highPrice": 59.95,
        "marketPrice": 32.46,
        "directLowPrice": null
      }
    ]
  },
  {
    "productId": 231306,
    "name": "First Partner Pack (Kanto)",
    "cleanName": "First Partner Pack Kanto",
    "imageUrl": "https://tcgplayer-cdn.tcgplayer.com/product/231306_200w.jpg",
    "categoryId": 3,
    "groupId": 2776,
    "url": "https://www.tcgplayer.com/product/231306/pokemon-first-partner-pack-first-partner-pack-kanto",
    "modifiedOn": "2021-10-22T04:03:10.91",
    "imageCount": 1,
    "presaleInfo": {
      "isPresale": false,
      "releasedOn": "2021-03-05T00:00:00",
      "note": null
    },
    "extendedData": [
      {
        "name": "CardText",
        "displayName": "Card Text",
        "value": "Includes three oversize promo cards featuring the first partner Pokeémon of the Kanto region—Bulbasaur, Charmander, and Squirtle—plus two regular Pokémon TCG boosters."
      },
      {
        "name": "UPC",
        "displayName": "UPC",
        "value": "0820650819681"
      }
    ],
    "prices": [
      {
        "subTypeName": "Normal",
        "lowPrice": 30.01,
        "midPrice": 39.98,
        "highPrice": 60,
        "marketPrice": 32.71,
        "directLowPrice": null
      }
    ]
  },
  {
    "productId": 231307,
    "name": "Bulbasaur",
    "cleanName": "Bulbasaur",
    "imageUrl": "https://tcgplayer-cdn.tcgplayer.com/product/231307_200w.jpg",
    "categoryId": 3,
    "groupId": 2776,
    "url": "https://www.tcgplayer.com/product/231307/pokemon-first-partner-pack-bulbasaur",
    "modifiedOn": "2021-12-31T13:03:26.363",
    "imageCount": 1,
    "presaleInfo": {
      "isPresale": false,
      "releasedOn": null,
      "note": null
    },
    "extendedData": [
      {
        "name": "Number",
        "displayName": "Card Number",
        "value": "044/102"
      },
      {
        "name": "Rarity",
        "displayName": "Rarity",
        "value": "Promo"
      },
      {
        "name": "Card Type",
        "displayName": "Card Type",
        "value": "Grass"
      },
      {
        "name": "HP",
        "displayName": "HP",
        "value": "40"
      },
      {
        "name": "Stage",
        "displayName": "Stage",
        "value": "Basic"
      },
      {
        "name": "Attack 1",
        "displayName": "Attack 1",
        "value": "[GG] Leech Seed (20)\r\n<br>Unless all damage from this attack is prevented, you may remove 1 damage counter from Bulbasaur."
      },
      {
        "name": "Weakness",
        "displayName": "Weakness",
        "value": "R"
      },
      {
        "name": "Resistance",
        "displayName": "Resistance",
        "value": "None"
      },
      {
        "name": "RetreatCost",
        "displayName": "Retreat Cost",
        "value": "1"
      }
    ],
    "prices": [
      {
        "subTypeName": "Normal",
        "lowPrice": 1.25,
        "midPrice": 2.94,
        "highPrice": 49.99,
        "marketPrice": 2.59,
        "directLowPrice": null
      }
    ]
  },
  {
    "productId": 231451,
    "name": "Charmander",
    "cleanName": "Charmander",
    "imageUrl": "https://tcgplayer-cdn.tcgplayer.com/product/231451_200w.jpg",
    "categoryId": 3,
    "groupId": 2776,
    "url": "https://www.tcgplayer.com/product/231451/pokemon-first-partner-pack-charmander",
    "modifiedOn": "2021-12-31T13:03:55.417",
    "imageCount": 1,
    "presaleInfo": {
      "isPresale": false,
      "releasedOn": null,
      "note": null
    },
    "extendedData": [
      {
        "name": "Number",
        "displayName": "Card Number",
        "value": "046/102"
      },
      {
        "name": "Rarity",
        "displayName": "Rarity",
        "value": "Promo"
      },
      {
        "name": "Card Type",
        "displayName": "Card Type",
        "value": "Fire"
      },
      {
        "name": "HP",
        "displayName": "HP",
        "value": "50"
      },
      {
        "name": "Stage",
        "displayName": "Stage",
        "value": "Basic"
      },
      {
        "name": "Attack 1",
        "displayName": "Attack 1",
        "value": "[1] Scratch (10)"
      },
      {
        "name": "Attack 2",
        "displayName": "Attack 2",
        "value": "[1R] Ember (30)\r\n<br>Discard 1 R Energy card attached to Charmander in order to use this attack."
      },
      {
        "name": "Weakness",
        "displayName": "Weakness",
        "value": "W"
      },
      {
        "name": "Resistance",
        "displayName": "Resistance",
        "value": "None"
      },
      {
        "name": "RetreatCost",
        "displayName": "Retreat Cost",
        "value": "1"
      }
    ],
    "prices": [
      {
        "subTypeName": "Normal",
        "lowPrice": 0.85,
        "midPrice": 1.5,
        "highPrice": 10,
        "marketPrice": 1.41,
        "directLowPrice": null
      }
    ]
  },
  {
    "productId": 231452,
    "name": "Chespin",
    "cleanName": "Chespin",
    "imageUrl": "https://tcgplayer-cdn.tcgplayer.com/product/231452_200w.jpg",
    "categoryId": 3,
    "groupId": 2776,
    "url": "https://www.tcgplayer.com/product/231452/pokemon-first-partner-pack-chespin",
    "modifiedOn": "2021-05-07T04:03:11.703",
    "imageCount": 1,
    "presaleInfo": {
      "isPresale": false,
      "releasedOn": "2021-03-05T00:00:00",
      "note": null
    },
    "extendedData": [
      {
        "name": "Number",
        "displayName": "Card Number",
        "value": "XY01"
      },
      {
        "name": "Rarity",
        "displayName": "Rarity",
        "value": "Promo"
      },
      {
        "name": "Card Type",
        "displayName": "Card Type",
        "value": "Grass"
      },
      {
        "name": "HP",
        "displayName": "HP",
        "value": "60"
      },
      {
        "name": "Stage",
        "displayName": "Stage",
        "value": "Basic"
      },
      {
        "name": "Attack 1",
        "displayName": "Attack 1",
        "value": "[G] Vine Whip (10)"
      },
      {
        "name": "Attack 2",
        "displayName": "Attack 2",
        "value": "[1G] Seed Bomb (20)"
      },
      {
        "name": "Weakness",
        "displayName": "Weakness",
        "value": "Rx2"
      },
      {
        "name": "Resistance",
        "displayName": "Resistance",
        "value": "None"
      },
      {
        "name": "RetreatCost",
        "displayName": "Retreat Cost",
        "value": "1"
      }
    ],
    "prices": [
      {
        "subTypeName": "Normal",
        "lowPrice": 0.7,
        "midPrice": 1.77,
        "highPrice": 10,
        "marketPrice": 1.55,
        "directLowPrice": null
      }
    ]
  },
  {
    "productId": 231453,
    "name": "Chikorita",
    "cleanName": "Chikorita",
    "imageUrl": "https://tcgplayer-cdn.tcgplayer.com/product/231453_200w.jpg",
    "categoryId": 3,
    "groupId": 2776,
    "url": "https://www.tcgplayer.com/product/231453/pokemon-first-partner-pack-chikorita",
    "modifiedOn": "2022-02-09T14:04:04.583",
    "imageCount": 1,
    "presaleInfo": {
      "isPresale": false,
      "releasedOn": null,
      "note": null
    },
    "extendedData": [
      {
        "name": "Number",
        "displayName": "Card Number",
        "value": "054/111"
      },
      {
        "name": "Rarity",
        "displayName": "Rarity",
        "value": "Promo"
      },
      {
        "name": "Card Type",
        "displayName": "Card Type",
        "value": "Grass"
      },
      {
        "name": "HP",
        "displayName": "HP",
        "value": "50"
      },
      {
        "name": "Stage",
        "displayName": "Stage",
        "value": "Basic"
      },
      {
        "name": "Attack 1",
        "displayName": "Attack 1",
        "value": "[1] Growl\r\n<br>If the Defending Pokemon attacks Chikorita during your opponent's next turn, any damage done to Chikorita is reduced by 10 <em>(before applying Weakness and Resistance)</em>. <em>(Benching or evolving either Pokemon ends this effect.)</em>"
      },
      {
        "name": "Attack 2",
        "displayName": "Attack 2",
        "value": "[1G] Razor Leaf (20)"
      },
      {
        "name": "Weakness",
        "displayName": "Weakness",
        "value": "R"
      },
      {
        "name": "Resistance",
        "displayName": "Resistance",
        "value": "None"
      },
      {
        "name": "RetreatCost",
        "displayName": "Retreat Cost",
        "value": "1"
      }
    ],
    "prices": [
      {
        "subTypeName": "Normal",
        "lowPrice": 0.95,
        "midPrice": 1.44,
        "highPrice": 10,
        "marketPrice": 1.26,
        "directLowPrice": null
      }
    ]
  },
  {
    "productId": 231454,
    "name": "Chimchar",
    "cleanName": "Chimchar",
    "imageUrl": "https://tcgplayer-cdn.tcgplayer.com/product/231454_200w.jpg",
    "categoryId": 3,
    "groupId": 2776,
    "url": "https://www.tcgplayer.com/product/231454/pokemon-first-partner-pack-chimchar",
    "modifiedOn": "2021-07-09T04:03:08.203",
    "imageCount": 1,
    "presaleInfo": {
      "isPresale": false,
      "releasedOn": "2021-03-05T00:00:00",
      "note": null
    },
    "extendedData": [
      {
        "name": "Number",
        "displayName": "Card Number",
        "value": "076/130"
      },
      {
        "name": "Rarity",
        "displayName": "Rarity",
        "value": "Promo"
      },
      {
        "name": "Card Type",
        "displayName": "Card Type",
        "value": "Fire"
      },
      {
        "name": "HP",
        "displayName": "HP",
        "value": "50"
      },
      {
        "name": "Stage",
        "displayName": "Stage",
        "value": "Basic"
      },
      {
        "name": "Attack 1",
        "displayName": "Attack 1",
        "value": "[0] Scratch (10)"
      },
      {
        "name": "Attack 2",
        "displayName": "Attack 2",
        "value": "[1R] Ember (30)\r\n<br>Flip a coin. If tails, discard a R Energy attached to Chimchar."
      },
      {
        "name": "Weakness",
        "displayName": "Weakness",
        "value": "W+10"
      },
      {
        "name": "Resistance",
        "displayName": "Resistance",
        "value": "None"
      },
      {
        "name": "RetreatCost",
        "displayName": "Retreat Cost",
        "value": "1"
      }
    ],
    "prices": [
      {
        "subTypeName": "Normal",
        "lowPrice": 0.5,
        "midPrice": 1,
        "highPrice": 4.99,
        "marketPrice": 1,
        "directLowPrice": null
      }
    ]
  },
  {
    "productId": 231455,
    "name": "Cyndaquil",
    "cleanName": "Cyndaquil",
    "imageUrl": "https://tcgplayer-cdn.tcgplayer.com/product/231455_200w.jpg",
    "categoryId": 3,
    "groupId": 2776,
    "url": "https://www.tcgplayer.com/product/231455/pokemon-first-partner-pack-cyndaquil",
    "modifiedOn": "2022-02-09T14:04:39.027",
    "imageCount": 1,
    "presaleInfo": {
      "isPresale": false,
      "releasedOn": null,
      "note": null
    },
    "extendedData": [
      {
        "name": "Number",
        "displayName": "Card Number",
        "value": "057/111"
      },
      {
        "name": "Rarity",
        "displayName": "Rarity",
        "value": "Promo"
      },
      {
        "name": "Card Type",
        "displayName": "Card Type",
        "value": "Fire"
      },
      {
        "name": "HP",
        "displayName": "HP",
        "value": "50"
      },
      {
        "name": "Stage",
        "displayName": "Stage",
        "value": "Basic"
      },
      {
        "name": "Attack 1",
        "displayName": "Attack 1",
        "value": "[R] Fireworks (20)\r\n<br>Flip a coin. If tails, discard 1 Energy card attached to Cyndaquil."
      },
      {
        "name": "Attack 2",
        "displayName": "Attack 2",
        "value": "[2] Quick Attack (10+)\r\n<br>Flip a coin. If heads, this attack does 10 damage plus 20 more damage; if tails, this attack does 10 damage."
      },
      {
        "name": "Weakness",
        "displayName": "Weakness",
        "value": "W"
      },
      {
        "name": "Resistance",
        "displayName": "Resistance",
        "value": "None"
      },
      {
        "name": "RetreatCost",
        "displayName": "Retreat Cost",
        "value": "1"
      }
    ],
    "prices": [
      {
        "subTypeName": "Normal",
        "lowPrice": 0.8,
        "midPrice": 1.36,
        "highPrice": 10,
        "marketPrice": 1.35,
        "directLowPrice": null
      }
    ]
  },
  {
    "productId": 231456,
    "name": "Fennekin",
    "cleanName": "Fennekin",
    "imageUrl": "https://tcgplayer-cdn.tcgplayer.com/product/231456_200w.jpg",
    "categoryId": 3,
    "groupId": 2776,
    "url": "https://www.tcgplayer.com/product/231456/pokemon-first-partner-pack-fennekin",
    "modifiedOn": "2022-02-15T17:48:57.933",
    "imageCount": 1,
    "presaleInfo": {
      "isPresale": false,
      "releasedOn": null,
      "note": null
    },
    "extendedData": [
      {
        "name": "Number",
        "displayName": "Card Number",
        "value": "XY02"
      },
      {
        "name": "Rarity",
        "displayName": "Rarity",
        "value": "Promo"
      },
      {
        "name": "Card Type",
        "displayName": "Card Type",
        "value": "Fire"
      },
      {
        "name": "HP",
        "displayName": "HP",
        "value": "60"
      },
      {
        "name": "Stage",
        "displayName": "Stage",
        "value": "Basic"
      },
      {
        "name": "Attack 1",
        "displayName": "Attack 1",
        "value": "[R] Scratch (10)"
      },
      {
        "name": "Attack 2",
        "displayName": "Attack 2",
        "value": "[1R] Live Coal (20)"
      },
      {
        "name": "Weakness",
        "displayName": "Weakness",
        "value": "Wx2"
      },
      {
        "name": "Resistance",
        "displayName": "Resistance",
        "value": "None"
      },
      {
        "name": "RetreatCost",
        "displayName": "Retreat Cost",
        "value": "1"
      }
    ],
    "prices": [
      {
        "subTypeName": "Normal",
        "lowPrice": 0.74,
        "midPrice": 1.78,
        "highPrice": 10,
        "marketPrice": 1.57,
        "directLowPrice": null
      }
    ]
  },
  {
    "productId": 231457,
    "name": "Froakie",
    "cleanName": "Froakie",
    "imageUrl": "https://tcgplayer-cdn.tcgplayer.com/product/231457_200w.jpg",
    "categoryId": 3,
    "groupId": 2776,
    "url": "https://www.tcgplayer.com/product/231457/pokemon-first-partner-pack-froakie",
    "modifiedOn": "2021-05-07T04:03:11.703",
    "imageCount": 1,
    "presaleInfo": {
      "isPresale": false,
      "releasedOn": "2021-03-05T00:00:00",
      "note": null
    },
    "extendedData": [
      {
        "name": "Number",
        "displayName": "Card Number",
        "value": "XY03"
      },
      {
        "name": "Rarity",
        "displayName": "Rarity",
        "value": "Promo"
      },
      {
        "name": "Card Type",
        "displayName": "Card Type",
        "value": "Water"
      },
      {
        "name": "HP",
        "displayName": "HP",
        "value": "60"
      },
      {
        "name": "Stage",
        "displayName": "Stage",
        "value": "Basic"
      },
      {
        "name": "Attack 1",
        "displayName": "Attack 1",
        "value": "[W] Pound (10)"
      },
      {
        "name": "Attack 2",
        "displayName": "Attack 2",
        "value": "[1W] Water Drip (20)"
      },
      {
        "name": "Weakness",
        "displayName": "Weakness",
        "value": "Gx2"
      },
      {
        "name": "Resistance",
        "displayName": "Resistance",
        "value": "None"
      },
      {
        "name": "RetreatCost",
        "displayName": "Retreat Cost",
        "value": "1"
      }
    ],
    "prices": [
      {
        "subTypeName": "Normal",
        "lowPrice": 1,
        "midPrice": 2.11,
        "highPrice": 10,
        "marketPrice": 1.9,
        "directLowPrice": null
      }
    ]
  },
  {
    "productId": 231458,
    "name": "Grookey",
    "cleanName": "Grookey",
    "imageUrl": "https://tcgplayer-cdn.tcgplayer.com/product/231458_200w.jpg",
    "categoryId": 3,
    "groupId": 2776,
    "url": "https://www.tcgplayer.com/product/231458/pokemon-first-partner-pack-grookey",
    "modifiedOn": "2021-03-05T05:03:21.527",
    "imageCount": 1,
    "presaleInfo": {
      "isPresale": false,
      "releasedOn": "2021-03-05T00:00:00",
      "note": null
    },
    "extendedData": [
      {
        "name": "Number",
        "displayName": "Card Number",
        "value": "SWSH001"
      },
      {
        "name": "Rarity",
        "displayName": "Rarity",
        "value": "Promo"
      },
      {
        "name": "Card Type",
        "displayName": "Card Type",
        "value": "Grass"
      },
      {
        "name": "HP",
        "displayName": "HP",
        "value": "60"
      },
      {
        "name": "Stage",
        "displayName": "Stage",
        "value": "Basic"
      },
      {
        "name": "Attack 1",
        "displayName": "Attack 1",
        "value": "[1G] Branch Poke (30)"
      },
      {
        "name": "Weakness",
        "displayName": "Weakness",
        "value": "Rx2"
      },
      {
        "name": "Resistance",
        "displayName": "Resistance",
        "value": "None"
      },
      {
        "name": "RetreatCost",
        "displayName": "Retreat Cost",
        "value": "1"
      }
    ],
    "prices": [
      {
        "subTypeName": "Normal",
        "lowPrice": 0.75,
        "midPrice": 1.99,
        "highPrice": 7.78,
        "marketPrice": 1.81,
        "directLowPrice": null
      }
    ]
  },
  {
    "productId": 231459,
    "name": "Litten",
    "cleanName": "Litten",
    "imageUrl": "https://tcgplayer-cdn.tcgplayer.com/product/231459_200w.jpg",
    "categoryId": 3,
    "groupId": 2776,
    "url": "https://www.tcgplayer.com/product/231459/pokemon-first-partner-pack-litten",
    "modifiedOn": "2021-04-02T04:03:07.323",
    "imageCount": 1,
    "presaleInfo": {
      "isPresale": false,
      "releasedOn": "2021-03-05T00:00:00",
      "note": null
    },
    "extendedData": [
      {
        "name": "Number",
        "displayName": "Card Number",
        "value": "SM02"
      },
      {
        "name": "Rarity",
        "displayName": "Rarity",
        "value": "Promo"
      },
      {
        "name": "Card Type",
        "displayName": "Card Type",
        "value": "Fire"
      },
      {
        "name": "HP",
        "displayName": "HP",
        "value": "60"
      },
      {
        "name": "Stage",
        "displayName": "Stage",
        "value": "Basic"
      },
      {
        "name": "Attack 1",
        "displayName": "Attack 1",
        "value": "[1R] Combustion (30)"
      },
      {
        "name": "Weakness",
        "displayName": "Weakness",
        "value": "Wx2"
      },
      {
        "name": "Resistance",
        "displayName": "Resistance",
        "value": "None"
      },
      {
        "name": "RetreatCost",
        "displayName": "Retreat Cost",
        "value": "1"
      }
    ],
    "prices": [
      {
        "subTypeName": "Normal",
        "lowPrice": 1.65,
        "midPrice": 2.5,
        "highPrice": 7.99,
        "marketPrice": 2.4,
        "directLowPrice": null
      }
    ]
  },
  {
    "productId": 231460,
    "name": "Mudkip",
    "cleanName": "Mudkip",
    "imageUrl": "https://tcgplayer-cdn.tcgplayer.com/product/231460_200w.jpg",
    "categoryId": 3,
    "groupId": 2776,
    "url": "https://www.tcgplayer.com/product/231460/pokemon-first-partner-pack-mudkip",
    "modifiedOn": "2021-08-12T04:03:07.89",
    "imageCount": 1,
    "presaleInfo": {
      "isPresale": false,
      "releasedOn": "2021-03-05T00:00:00",
      "note": null
    },
    "extendedData": [
      {
        "name": "Number",
        "displayName": "Card Number",
        "value": "059/109"
      },
      {
        "name": "Rarity",
        "displayName": "Rarity",
        "value": "Promo"
      },
      {
        "name": "Card Type",
        "displayName": "Card Type",
        "value": "Water"
      },
      {
        "name": "HP",
        "displayName": "HP",
        "value": "50"
      },
      {
        "name": "Stage",
        "displayName": "Stage",
        "value": "Basic"
      },
      {
        "name": "Attack 1",
        "displayName": "Attack 1",
        "value": "[W] Bubble (10)\r\n<br>Flip a coin. If heads, the Defending Pokemon is now Paralyzed."
      },
      {
        "name": "Weakness",
        "displayName": "Weakness",
        "value": "L"
      },
      {
        "name": "Resistance",
        "displayName": "Resistance",
        "value": "None"
      },
      {
        "name": "RetreatCost",
        "displayName": "Retreat Cost",
        "value": "1"
      }
    ],
    "prices": [
      {
        "subTypeName": "Normal",
        "lowPrice": 0.6,
        "midPrice": 2.12,
        "highPrice": 9.99,
        "marketPrice": 2.12,
        "directLowPrice": null
      }
    ]
  },
  {
    "productId": 231461,
    "name": "Oshawott",
    "cleanName": "Oshawott",
    "imageUrl": "https://tcgplayer-cdn.tcgplayer.com/product/231461_200w.jpg",
    "categoryId": 3,
    "groupId": 2776,
    "url": "https://www.tcgplayer.com/product/231461/pokemon-first-partner-pack-oshawott",
    "modifiedOn": "2021-06-04T04:03:36.873",
    "imageCount": 1,
    "presaleInfo": {
      "isPresale": false,
      "releasedOn": "2021-03-05T00:00:00",
      "note": null
    },
    "extendedData": [
      {
        "name": "Number",
        "displayName": "Card Number",
        "value": "BW03"
      },
      {
        "name": "Rarity",
        "displayName": "Rarity",
        "value": "Promo"
      },
      {
        "name": "Card Type",
        "displayName": "Card Type",
        "value": "Water"
      },
      {
        "name": "HP",
        "displayName": "HP",
        "value": "60"
      },
      {
        "name": "Stage",
        "displayName": "Stage",
        "value": "Basic"
      },
      {
        "name": "Attack 1",
        "displayName": "Attack 1",
        "value": "[1W] Water Pulse (20)\r\n<br>Flip a coin. If heads, the Defending Pokemon is now Asleep."
      },
      {
        "name": "Weakness",
        "displayName": "Weakness",
        "value": "Lx2"
      },
      {
        "name": "Resistance",
        "displayName": "Resistance",
        "value": "None"
      },
      {
        "name": "RetreatCost",
        "displayName": "Retreat Cost",
        "value": "1"
      }
    ],
    "prices": [
      {
        "subTypeName": "Normal",
        "lowPrice": 0.7,
        "midPrice": 1.24,
        "highPrice": 5.95,
        "marketPrice": 1.24,
        "directLowPrice": null
      }
    ]
  },
  {
    "productId": 231463,
    "name": "Piplup",
    "cleanName": "Piplup",
    "imageUrl": "https://tcgplayer-cdn.tcgplayer.com/product/231463_200w.jpg",
    "categoryId": 3,
    "groupId": 2776,
    "url": "https://www.tcgplayer.com/product/231463/pokemon-first-partner-pack-piplup",
    "modifiedOn": "2021-07-09T04:03:08.203",
    "imageCount": 1,
    "presaleInfo": {
      "isPresale": false,
      "releasedOn": "2021-03-05T00:00:00",
      "note": null
    },
    "extendedData": [
      {
        "name": "Number",
        "displayName": "Card Number",
        "value": "093/130"
      },
      {
        "name": "Rarity",
        "displayName": "Rarity",
        "value": "Promo"
      },
      {
        "name": "Card Type",
        "displayName": "Card Type",
        "value": "Water"
      },
      {
        "name": "HP",
        "displayName": "HP",
        "value": "60"
      },
      {
        "name": "Stage",
        "displayName": "Stage",
        "value": "Basic"
      },
      {
        "name": "Attack 1",
        "displayName": "Attack 1",
        "value": "[0] Peck (10)"
      },
      {
        "name": "Attack 2",
        "displayName": "Attack 2",
        "value": "[1W] Water Splash (20+)\r\n<br>Flip a coin. If heads, this attack does 20 damage plus 10 more damage."
      },
      {
        "name": "Weakness",
        "displayName": "Weakness",
        "value": "L+10"
      },
      {
        "name": "Resistance",
        "displayName": "Resistance",
        "value": "None"
      },
      {
        "name": "RetreatCost",
        "displayName": "Retreat Cost",
        "value": "1"
      }
    ],
    "prices": [
      {
        "subTypeName": "Normal",
        "lowPrice": 0.8,
        "midPrice": 1.84,
        "highPrice": 6.02,
        "marketPrice": 1.79,
        "directLowPrice": null
      }
    ]
  },
  {
    "productId": 231464,
    "name": "Popplio",
    "cleanName": "Popplio",
    "imageUrl": "https://tcgplayer-cdn.tcgplayer.com/product/231464_200w.jpg",
    "categoryId": 3,
    "groupId": 2776,
    "url": "https://www.tcgplayer.com/product/231464/pokemon-first-partner-pack-popplio",
    "modifiedOn": "2021-04-02T04:03:07.323",
    "imageCount": 1,
    "presaleInfo": {
      "isPresale": false,
      "releasedOn": "2021-03-05T00:00:00",
      "note": null
    },
    "extendedData": [
      {
        "name": "Number",
        "displayName": "Card Number",
        "value": "SM03"
      },
      {
        "name": "Rarity",
        "displayName": "Rarity",
        "value": "Promo"
      },
      {
        "name": "Card Type",
        "displayName": "Card Type",
        "value": "Water"
      },
      {
        "name": "HP",
        "displayName": "HP",
        "value": "60"
      },
      {
        "name": "Stage",
        "displayName": "Stage",
        "value": "Basic"
      },
      {
        "name": "Attack 1",
        "displayName": "Attack 1",
        "value": "[W] Sing\r\n<br>Your opponent's Active Pokemon is now Asleep."
      },
      {
        "name": "Weakness",
        "displayName": "Weakness",
        "value": "Gx2"
      },
      {
        "name": "Resistance",
        "displayName": "Resistance",
        "value": "None"
      },
      {
        "name": "RetreatCost",
        "displayName": "Retreat Cost",
        "value": "1"
      }
    ],
    "prices": [
      {
        "subTypeName": "Normal",
        "lowPrice": 0.25,
        "midPrice": 2.17,
        "highPrice": 6.95,
        "marketPrice": 1.84,
        "directLowPrice": null
      }
    ]
  },
  {
    "productId": 231465,
    "name": "Rowlet",
    "cleanName": "Rowlet",
    "imageUrl": "https://tcgplayer-cdn.tcgplayer.com/product/231465_200w.jpg",
    "categoryId": 3,
    "groupId": 2776,
    "url": "https://www.tcgplayer.com/product/231465/pokemon-first-partner-pack-rowlet",
    "modifiedOn": "2021-04-02T04:03:07.323",
    "imageCount": 1,
    "presaleInfo": {
      "isPresale": false,
      "releasedOn": "2021-03-05T00:00:00",
      "note": null
    },
    "extendedData": [
      {
        "name": "Number",
        "displayName": "Card Number",
        "value": "SM01"
      },
      {
        "name": "Rarity",
        "displayName": "Rarity",
        "value": "Promo"
      },
      {
        "name": "Card Type",
        "displayName": "Card Type",
        "value": "Grass"
      },
      {
        "name": "HP",
        "displayName": "HP",
        "value": "50"
      },
      {
        "name": "Stage",
        "displayName": "Stage",
        "value": "Basic"
      },
      {
        "name": "Attack 1",
        "displayName": "Attack 1",
        "value": "[G] Fury Attack (10x)\r\n<br>Flip 3 coins. This attack does 10 damage for each heads."
      },
      {
        "name": "Weakness",
        "displayName": "Weakness",
        "value": "Rx2"
      },
      {
        "name": "Resistance",
        "displayName": "Resistance",
        "value": "None"
      },
      {
        "name": "RetreatCost",
        "displayName": "Retreat Cost",
        "value": "1"
      }
    ],
    "prices": [
      {
        "subTypeName": "Normal",
        "lowPrice": 1.75,
        "midPrice": 2.78,
        "highPrice": 6.95,
        "marketPrice": 2.52,
        "directLowPrice": null
      }
    ]
  },
  {
    "productId": 231466,
    "name": "Scorbunny",
    "cleanName": "Scorbunny",
    "imageUrl": "https://tcgplayer-cdn.tcgplayer.com/product/231466_200w.jpg",
    "categoryId": 3,
    "groupId": 2776,
    "url": "https://www.tcgplayer.com/product/231466/pokemon-first-partner-pack-scorbunny",
    "modifiedOn": "2022-02-15T17:49:35.447",
    "imageCount": 1,
    "presaleInfo": {
      "isPresale": false,
      "releasedOn": null,
      "note": null
    },
    "extendedData": [
      {
        "name": "Number",
        "displayName": "Card Number",
        "value": "SWSH002"
      },
      {
        "name": "Rarity",
        "displayName": "Rarity",
        "value": "Promo"
      },
      {
        "name": "Card Type",
        "displayName": "Card Type",
        "value": "Fire"
      },
      {
        "name": "HP",
        "displayName": "HP",
        "value": "60"
      },
      {
        "name": "Stage",
        "displayName": "Stage",
        "value": "Basic"
      },
      {
        "name": "Attack 1",
        "displayName": "Attack 1",
        "value": "[R] Super Singe (10)\r\n<br>Flip a coin. If heads, your opponent's Active Pokemon is is now Burned."
      },
      {
        "name": "Weakness",
        "displayName": "Weakness",
        "value": "Wx2"
      },
      {
        "name": "Resistance",
        "displayName": "Resistance",
        "value": "None"
      },
      {
        "name": "RetreatCost",
        "displayName": "Retreat Cost",
        "value": "1"
      }
    ],
    "prices": [
      {
        "subTypeName": "Normal",
        "lowPrice": 2,
        "midPrice": 3.01,
        "highPrice": 7.44,
        "marketPrice": 2.78,
        "directLowPrice": null
      }
    ]
  },
  {
    "productId": 231467,
    "name": "Snivy",
    "cleanName": "Snivy",
    "imageUrl": "https://tcgplayer-cdn.tcgplayer.com/product/231467_200w.jpg",
    "categoryId": 3,
    "groupId": 2776,
    "url": "https://www.tcgplayer.com/product/231467/pokemon-first-partner-pack-snivy",
    "modifiedOn": "2021-12-29T15:29:30.197",
    "imageCount": 1,
    "presaleInfo": {
      "isPresale": false,
      "releasedOn": null,
      "note": null
    },
    "extendedData": [
      {
        "name": "Number",
        "displayName": "Card Number",
        "value": "BW01"
      },
      {
        "name": "Rarity",
        "displayName": "Rarity",
        "value": "Promo"
      },
      {
        "name": "Card Type",
        "displayName": "Card Type",
        "value": "Grass"
      },
      {
        "name": "HP",
        "displayName": "HP",
        "value": "60"
      },
      {
        "name": "Stage",
        "displayName": "Stage",
        "value": "Basic"
      },
      {
        "name": "Attack 1",
        "displayName": "Attack 1",
        "value": "[1G] Slam (20x)\r\n<br>Flip 2 coins. This attack does 20 damage times the number of heads."
      },
      {
        "name": "Weakness",
        "displayName": "Weakness",
        "value": "Rx2"
      },
      {
        "name": "Resistance",
        "displayName": "Resistance",
        "value": "W-20"
      },
      {
        "name": "RetreatCost",
        "displayName": "Retreat Cost",
        "value": "1"
      }
    ],
    "prices": [
      {
        "subTypeName": "Normal",
        "lowPrice": 0.6,
        "midPrice": 0.99,
        "highPrice": 5,
        "marketPrice": 0.89,
        "directLowPrice": null
      }
    ]
  },
  {
    "productId": 231468,
    "name": "Sobble",
    "cleanName": "Sobble",
    "imageUrl": "https://tcgplayer-cdn.tcgplayer.com/product/231468_200w.jpg",
    "categoryId": 3,
    "groupId": 2776,
    "url": "https://www.tcgplayer.com/product/231468/pokemon-first-partner-pack-sobble",
    "modifiedOn": "2022-03-05T21:11:40.413",
    "imageCount": 1,
    "presaleInfo": {
      "isPresale": false,
      "releasedOn": null,
      "note": null
    },
    "extendedData": [
      {
        "name": "Number",
        "displayName": "Card Number",
        "value": "SWSH003"
      },
      {
        "name": "Rarity",
        "displayName": "Rarity",
        "value": "Promo"
      },
      {
        "name": "Card Type",
        "displayName": "Card Type",
        "value": "Water"
      },
      {
        "name": "HP",
        "displayName": "HP",
        "value": "60"
      },
      {
        "name": "Stage",
        "displayName": "Stage",
        "value": "Basic"
      },
      {
        "name": "Attack 1",
        "displayName": "Attack 1",
        "value": "[1W] Bind (20)\r\n<br>Flip a coin. If heads, your opponent's Active Pokemon is now Paralyzed."
      },
      {
        "name": "Weakness",
        "displayName": "Weakness",
        "value": "Lx2"
      },
      {
        "name": "Resistance",
        "displayName": "Resistance",
        "value": "None"
      },
      {
        "name": "RetreatCost",
        "displayName": "Retreat Cost",
        "value": "1"
      }
    ],
    "prices": [
      {
        "subTypeName": "Normal",
        "lowPrice": 1,
        "midPrice": 1.74,
        "highPrice": 6.95,
        "marketPrice": 1.61,
        "directLowPrice": null
      }
    ]
  },
  {
    "productId": 231469,
    "name": "Squirtle",
    "cleanName": "Squirtle",
    "imageUrl": "https://tcgplayer-cdn.tcgplayer.com/product/231469_200w.jpg",
    "categoryId": 3,
    "groupId": 2776,
    "url": "https://www.tcgplayer.com/product/231469/pokemon-first-partner-pack-squirtle",
    "modifiedOn": "2022-02-15T17:47:52.247",
    "imageCount": 1,
    "presaleInfo": {
      "isPresale": false,
      "releasedOn": null,
      "note": null
    },
    "extendedData": [
      {
        "name": "Number",
        "displayName": "Card Number",
        "value": "063/102"
      },
      {
        "name": "Rarity",
        "displayName": "Rarity",
        "value": "Promo"
      },
      {
        "name": "Card Type",
        "displayName": "Card Type",
        "value": "Water"
      },
      {
        "name": "HP",
        "displayName": "HP",
        "value": "40"
      },
      {
        "name": "Stage",
        "displayName": "Stage",
        "value": "Basic"
      },
      {
        "name": "Attack 1",
        "displayName": "Attack 1",
        "value": "[W] Bubble (10)\r\n<br>Flip a coin. If heads, the Defending Pokemon is now Paralyzed."
      },
      {
        "name": "Attack 2",
        "displayName": "Attack 2",
        "value": "[1W] Withdraw\r\n<br>Flip a coin. If heads, prevent all damage done to Squirtle during your opponent's next turn. <em>(Any other effects of attacks still happen.)</em>"
      },
      {
        "name": "Weakness",
        "displayName": "Weakness",
        "value": "L"
      },
      {
        "name": "Resistance",
        "displayName": "Resistance",
        "value": "None"
      },
      {
        "name": "RetreatCost",
        "displayName": "Retreat Cost",
        "value": "1"
      }
    ],
    "prices": [
      {
        "subTypeName": "Normal",
        "lowPrice": 1.25,
        "midPrice": 2.5,
        "highPrice": 7.77,
        "marketPrice": 2.31,
        "directLowPrice": null
      }
    ]
  },
  {
    "productId": 231470,
    "name": "Tepig",
    "cleanName": "Tepig",
    "imageUrl": "https://tcgplayer-cdn.tcgplayer.com/product/231470_200w.jpg",
    "categoryId": 3,
    "groupId": 2776,
    "url": "https://www.tcgplayer.com/product/231470/pokemon-first-partner-pack-tepig",
    "modifiedOn": "2021-06-04T04:03:36.873",
    "imageCount": 1,
    "presaleInfo": {
      "isPresale": false,
      "releasedOn": "2021-03-05T00:00:00",
      "note": null
    },
    "extendedData": [
      {
        "name": "Number",
        "displayName": "Card Number",
        "value": "BW02"
      },
      {
        "name": "Rarity",
        "displayName": "Rarity",
        "value": "Promo"
      },
      {
        "name": "Card Type",
        "displayName": "Card Type",
        "value": "Fire"
      },
      {
        "name": "HP",
        "displayName": "HP",
        "value": "70"
      },
      {
        "name": "Stage",
        "displayName": "Stage",
        "value": "Basic"
      },
      {
        "name": "Attack 1",
        "displayName": "Attack 1",
        "value": "[1R] Ember (30)\r\n<br>Discard an Energy attached to this Pokemon."
      },
      {
        "name": "Weakness",
        "displayName": "Weakness",
        "value": "Wx2"
      },
      {
        "name": "Resistance",
        "displayName": "Resistance",
        "value": "None"
      },
      {
        "name": "RetreatCost",
        "displayName": "Retreat Cost",
        "value": "2"
      }
    ],
    "prices": [
      {
        "subTypeName": "Normal",
        "lowPrice": 0.35,
        "midPrice": 0.8,
        "highPrice": 5,
        "marketPrice": 0.75,
        "directLowPrice": null
      }
    ]
  },
  {
    "productId": 231471,
    "name": "Torchic",
    "cleanName": "Torchic",
    "imageUrl": "https://tcgplayer-cdn.tcgplayer.com/product/231471_200w.jpg",
    "categoryId": 3,
    "groupId": 2776,
    "url": "https://www.tcgplayer.com/product/231471/pokemon-first-partner-pack-torchic",
    "modifiedOn": "2021-08-12T04:03:07.89",
    "imageCount": 1,
    "presaleInfo": {
      "isPresale": false,
      "releasedOn": "2021-03-05T00:00:00",
      "note": null
    },
    "extendedData": [
      {
        "name": "Number",
        "displayName": "Card Number",
        "value": "074/109"
      },
      {
        "name": "Rarity",
        "displayName": "Rarity",
        "value": "Promo"
      },
      {
        "name": "Card Type",
        "displayName": "Card Type",
        "value": "Fire"
      },
      {
        "name": "HP",
        "displayName": "HP",
        "value": "50"
      },
      {
        "name": "Stage",
        "displayName": "Stage",
        "value": "Basic"
      },
      {
        "name": "Attack 1",
        "displayName": "Attack 1",
        "value": "[1] Singe\r\n<br>Flip a coin. If heads, the Defending Pokemon is now Burned."
      },
      {
        "name": "Weakness",
        "displayName": "Weakness",
        "value": "W"
      },
      {
        "name": "Resistance",
        "displayName": "Resistance",
        "value": "None"
      },
      {
        "name": "RetreatCost",
        "displayName": "Retreat Cost",
        "value": "1"
      }
    ],
    "prices": [
      {
        "subTypeName": "Normal",
        "lowPrice": 0.8,
        "midPrice": 1.97,
        "highPrice": 15,
        "marketPrice": 2.07,
        "directLowPrice": null
      }
    ]
  },
  {
    "productId": 231472,
    "name": "Totodile",
    "cleanName": "Totodile",
    "imageUrl": "https://tcgplayer-cdn.tcgplayer.com/product/231472_200w.jpg",
    "categoryId": 3,
    "groupId": 2776,
    "url": "https://www.tcgplayer.com/product/231472/pokemon-first-partner-pack-totodile",
    "modifiedOn": "2022-02-09T14:05:06.15",
    "imageCount": 1,
    "presaleInfo": {
      "isPresale": false,
      "releasedOn": null,
      "note": null
    },
    "extendedData": [
      {
        "name": "Number",
        "displayName": "Card Number",
        "value": "081/111"
      },
      {
        "name": "Rarity",
        "displayName": "Rarity",
        "value": "Promo"
      },
      {
        "name": "Card Type",
        "displayName": "Card Type",
        "value": "Water"
      },
      {
        "name": "HP",
        "displayName": "HP",
        "value": "50"
      },
      {
        "name": "Stage",
        "displayName": "Stage",
        "value": "Basic"
      },
      {
        "name": "Attack 1",
        "displayName": "Attack 1",
        "value": "[1] Leer\r\n<br>Flip a coin. If heads, the Defending Pokemon can't attack Totodile during your opponent's next turn. <em>(Benching or evolving either Pokemon ends this effect.)</em>"
      },
      {
        "name": "Attack 2",
        "displayName": "Attack 2",
        "value": "[W] Fury Swipes (10x)\r\n<br>Flip 3 coins. This attack does 10 damage times the number of heads."
      },
      {
        "name": "Weakness",
        "displayName": "Weakness",
        "value": "G"
      },
      {
        "name": "Resistance",
        "displayName": "Resistance",
        "value": "None"
      },
      {
        "name": "RetreatCost",
        "displayName": "Retreat Cost",
        "value": "1"
      }
    ],
    "prices": [
      {
        "subTypeName": "Normal",
        "lowPrice": 0.75,
        "midPrice": 1.24,
        "highPrice": 10,
        "marketPrice": 1.24,
        "directLowPrice": null
      }
    ]
  },
  {
    "productId": 231473,
    "name": "Treecko",
    "cleanName": "Treecko",
    "imageUrl": "https://tcgplayer-cdn.tcgplayer.com/product/231473_200w.jpg",
    "categoryId": 3,
    "groupId": 2776,
    "url": "https://www.tcgplayer.com/product/231473/pokemon-first-partner-pack-treecko",
    "modifiedOn": "2021-08-12T04:03:07.89",
    "imageCount": 1,
    "presaleInfo": {
      "isPresale": false,
      "releasedOn": "2021-03-05T00:00:00",
      "note": null
    },
    "extendedData": [
      {
        "name": "Number",
        "displayName": "Card Number",
        "value": "076/109"
      },
      {
        "name": "Rarity",
        "displayName": "Rarity",
        "value": "Promo"
      },
      {
        "name": "Card Type",
        "displayName": "Card Type",
        "value": "Grass"
      },
      {
        "name": "HP",
        "displayName": "HP",
        "value": "40"
      },
      {
        "name": "Stage",
        "displayName": "Stage",
        "value": "Basic"
      },
      {
        "name": "Attack 1",
        "displayName": "Attack 1",
        "value": "[1] Tail Slap (10)"
      },
      {
        "name": "Attack 2",
        "displayName": "Attack 2",
        "value": "[1G] Razor Leaf (20)"
      },
      {
        "name": "Weakness",
        "displayName": "Weakness",
        "value": "R"
      },
      {
        "name": "Resistance",
        "displayName": "Resistance",
        "value": "W-30"
      },
      {
        "name": "RetreatCost",
        "displayName": "Retreat Cost",
        "value": "1"
      }
    ],
    "prices": [
      {
        "subTypeName": "Normal",
        "lowPrice": 0.7,
        "midPrice": 1.52,
        "highPrice": 9.99,
        "marketPrice": 1.61,
        "directLowPrice": null
      }
    ]
  },
  {
    "productId": 231474,
    "name": "Turtwig",
    "cleanName": "Turtwig",
    "imageUrl": "https://tcgplayer-cdn.tcgplayer.com/product/231474_200w.jpg",
    "categoryId": 3,
    "groupId": 2776,
    "url": "https://www.tcgplayer.com/product/231474/pokemon-first-partner-pack-turtwig",
    "modifiedOn": "2021-07-09T04:03:08.203",
    "imageCount": 1,
    "presaleInfo": {
      "isPresale": false,
      "releasedOn": "2021-03-05T00:00:00",
      "note": null
    },
    "extendedData": [
      {
        "name": "Number",
        "displayName": "Card Number",
        "value": "103/130"
      },
      {
        "name": "Rarity",
        "displayName": "Rarity",
        "value": "Promo"
      },
      {
        "name": "Card Type",
        "displayName": "Card Type",
        "value": "Grass"
      },
      {
        "name": "HP",
        "displayName": "HP",
        "value": "60"
      },
      {
        "name": "Stage",
        "displayName": "Stage",
        "value": "Basic"
      },
      {
        "name": "Attack 1",
        "displayName": "Attack 1",
        "value": "[0] Tackle (10)"
      },
      {
        "name": "Attack 2",
        "displayName": "Attack 2",
        "value": "[G] Razor Leaf (20)"
      },
      {
        "name": "Weakness",
        "displayName": "Weakness",
        "value": "R+10"
      },
      {
        "name": "Resistance",
        "displayName": "Resistance",
        "value": "W-20"
      },
      {
        "name": "RetreatCost",
        "displayName": "Retreat Cost",
        "value": "2"
      }
    ],
    "prices": [
      {
        "subTypeName": "Normal",
        "lowPrice": 0.61,
        "midPrice": 1.43,
        "highPrice": 5.74,
        "marketPrice": 1.48,
        "directLowPrice": null
      }
    ]
  },
  {
    "productId": 261803,
    "name": "First Partner Packs [Set of 8] + Binder",
    "cleanName": "First Partner Packs Set of 8 plus Binder",
    "imageUrl": "https://tcgplayer-cdn.tcgplayer.com/product/261803_200w.jpg",
    "categoryId": 3,
    "groupId": 2776,
    "url": "https://www.tcgplayer.com/product/261803/pokemon-first-partner-pack-first-partner-packs-set-of-8-plus-binder",
    "modifiedOn": "2024-05-14T16:15:32.93",
    "imageCount": 5,
    "presaleInfo": {
      "isPresale": false,
      "releasedOn": null,
      "note": null
    },
    "extendedData": [
      {
        "name": "CardText",
        "displayName": "Card Text",
        "value": "Contents:\r\n<br>• x1 First Partner Pack (Kanto)\r\n<br>• x1 First Partner Pack (Johto)\r\n<br>• x1 First Partner Pack (Hoenn)\r\n<br>• x1 First Partner Pack (Sinnoh)\r\n<br>• x1 First Partner Pack (Unova)\r\n<br>• x1 First Partner Pack (Kalos)\r\n<br>• x1 First Partner Pack (Alola)\r\n<br>• x1 First Partner Pack (Galar)\r\n<br>• x1 First Partner Collector's Binder"
      }
    ],
    "prices": [
      {
        "subTypeName": "Normal",
        "lowPrice": 183.99,
        "midPrice": 207.49,
        "highPrice": 239.95,
        "marketPrice": 142.72,
        "directLowPrice": null
      }
    ]
  }
]