[
  {
    "productId": 232316,
    "name": "Bulbasaur - 1/25",
    "cleanName": "Bulbasaur 1 25",
    "imageUrl": "https://tcgplayer-cdn.tcgplayer.com/product/232316_200w.jpg",
    "categoryId": 3,
    "groupId": 2782,
    "url": "https://www.tcgplayer.com/product/232316/pokemon-mcdonalds-25th-anniversary-promos-bulbasaur-1-25",
    "modifiedOn": "2024-02-08T14:40:45.467",
    "imageCount": 1,
    "presaleInfo": {
      "isPresale": false,
      "releasedOn": null,
      "note": null
    },
    "extendedData": [
      {
        "name": "Number",
        "displayName": "Card Number",
        "value": "001/025"
      },
      {
        "name": "Rarity",
        "displayName": "Rarity",
        "value": "Promo"
      },
      {
        "name": "Card Type",
        "displayName": "Card Type",
        "value": "Grass"
      },
      {
        "name": "HP",
        "displayName": "HP",
        "value": "70"
      },
      {
        "name": "Stage",
        "displayName": "Stage",
        "value": "Basic"
      },
      {
        "name": "Attack 1",
        "displayName": "Attack 1",
        "value": "[1G] Razor Leaf (30)"
      },
      {
        "name": "Weakness",
        "displayName": "Weakness",
        "value": "Rx2"
      },
      {
        "name": "RetreatCost",
        "displayName": "Retreat Cost",
        "value": "2"
      }
    ],
    "prices": [
      {
        "subTypeName": "Normal",
        "lowPrice": 0.06,
        "midPrice": 0.5,
        "highPrice": 116.64,
        "marketPrice": 0.47,
        "directLowPrice": null
      },
      {
        "subTypeName": "Holofoil",
        "lowPrice": 1.62,
        "midPrice": 3.3,
        "highPrice": 9.07,
        "marketPrice": 3,
        "directLowPrice": 2.99
      }
    ]
  },
  {
    "productId": 232317,
    "name": "Chikorita - 2/25",
    "cleanName": "Chikorita 2 25",
    "imageUrl": "https://tcgplayer-cdn.tcgplayer.com/product/232317_200w.jpg",
    "categoryId": 3,
    "groupId": 2782,
    "url": "https://www.tcgplayer.com/product/232317/pokemon-mcdonalds-25th-anniversary-promos-chikorita-2-25",
    "modifiedOn": "2023-08-14T07:27:29.477",
    "imageCount": 1,
    "presaleInfo": {
      "isPresale": false,
      "releasedOn": null,
      "note": null
    },
    "extendedData": [
      {
        "name": "Number",
        "displayName": "Card Number",
        "value": "002/025"
      },
      {
        "name": "Rarity",
        "displayName": "Rarity",
        "value": "Promo"
      },
      {
        "name": "Card Type",
        "displayName": "Card Type",
        "value": "Grass"
      },
      {
        "name": "HP",
        "displayName": "HP",
        "value": "70"
      },
      {
        "name": "Stage",
        "displayName": "Stage",
        "value": "Basic"
      },
      {
        "name": "Attack 1",
        "displayName": "Attack 1",
        "value": "[G] Mini Drain (10)\r\n<br>Heal 10 damage from this Pokémon."
      },
      {
        "name": "Weakness",
        "displayName": "Weakness",
        "value": "Rx2"
      },
      {
        "name": "RetreatCost",
        "displayName": "Retreat Cost",
        "value": "1"
      }
    ],
    "prices": [
      {
        "subTypeName": "Holofoil",
        "lowPrice": 0.8,
        "midPrice": 1.26,
        "highPrice": 5.99,
        "marketPrice": 1.03,
        "directLowPrice": null
      },
      {
        "subTypeName": "Normal",
        "lowPrice": 0.09,
        "midPrice": 0.32,
        "highPrice": 4.95,
        "marketPrice": 0.3,
        "directLowPrice": null
      }
    ]
  },
  {
    "productId": 232318,
    "name": "Treecko - 3/25",
    "cleanName": "Treecko 3 25",
    "imageUrl": "https://tcgplayer-cdn.tcgplayer.com/product/232318_200w.jpg",
    "categoryId": 3,
    "groupId": 2782,
    "url": "https://www.tcgplayer.com/product/232318/pokemon-mcdonalds-25th-anniversary-promos-treecko-3-25",
    "modifiedOn": "2022-09-23T16:48:41.923",
    "imageCount": 1,
    "presaleInfo": {
      "isPresale": false,
      "releasedOn": null,
      "note": null
    },
    "extendedData": [
      {
        "name": "Number",
        "displayName": "Card Number",
        "value": "003/025"
      },
      {
        "name": "Rarity",
        "displayName": "Rarity",
        "value": "Promo"
      },
      {
        "name": "Card Type",
        "displayName": "Card Type",
        "value": "Grass"
      },
      {
        "name": "HP",
        "displayName": "HP",
        "value": "60"
      },
      {
        "name": "Stage",
        "displayName": "Stage",
        "value": "Basic"
      },
      {
        "name": "Attack 1",
        "displayName": "Attack 1",
        "value": "[G] Quick Attack (10+)\r\n<br>Flip a coin. If heads, this attack does 10 more damage."
      },
      {
        "name": "Weakness",
        "displayName": "Weakness",
        "value": "Rx2"
      },
      {
        "name": "RetreatCost",
        "displayName": "Retreat Cost",
        "value": "1"
      }
    ],
    "prices": [
      {
        "subTypeName": "Normal",
        "lowPrice": 0.05,
        "midPrice": 0.31,
        "highPrice": 4.95,
        "marketPrice": 0.27,
        "directLowPrice": null
      },
      {
        "subTypeName": "Holofoil",
        "lowPrice": 0.99,
        "midPrice": 2.12,
        "highPrice": 19.99,
        "marketPrice": 1.76,
        "directLowPrice": null
      }
    ]
  },
  {
    "productId": 232319,
    "name": "Turtwig - 4/25",
    "cleanName": "Turtwig 4 25",
    "imageUrl": "https://tcgplayer-cdn.tcgplayer.com/product/232319_200w.jpg",
    "categoryId": 3,
    "groupId": 2782,
    "url": "https://www.tcgplayer.com/product/232319/pokemon-mcdonalds-25th-anniversary-promos-turtwig-4-25",
    "modifiedOn": "2022-09-23T16:49:37.31",
    "imageCount": 1,
    "presaleInfo": {
      "isPresale": false,
      "releasedOn": null,
      "note": null
    },
    "extendedData": [
      {
        "name": "Number",
        "displayName": "Card Number",
        "value": "004/025"
      },
      {
        "name": "Rarity",
        "displayName": "Rarity",
        "value": "Promo"
      },
      {
        "name": "Card Type",
        "displayName": "Card Type",
        "value": "Grass"
      },
      {
        "name": "HP",
        "displayName": "HP",
        "value": "80"
      },
      {
        "name": "Stage",
        "displayName": "Stage",
        "value": "Basic"
      },
      {
        "name": "Attack 1",
        "displayName": "Attack 1",
        "value": "[2] Tackle (20)"
      },
      {
        "name": "Attack 2",
        "displayName": "Attack 2",
        "value": "[1GG] Razor Leaf (50)"
      },
      {
        "name": "Weakness",
        "displayName": "Weakness",
        "value": "Rx2"
      },
      {
        "name": "RetreatCost",
        "displayName": "Retreat Cost",
        "value": "2"
      }
    ],
    "prices": [
      {
        "subTypeName": "Normal",
        "lowPrice": 0.1,
        "midPrice": 0.39,
        "highPrice": 4.95,
        "marketPrice": 0.39,
        "directLowPrice": null
      },
      {
        "subTypeName": "Holofoil",
        "lowPrice": 0.61,
        "midPrice": 1.07,
        "highPrice": 5,
        "marketPrice": 0.98,
        "directLowPrice": null
      }
    ]
  },
  {
    "productId": 232320,
    "name": "Snivy - 5/25",
    "cleanName": "Snivy 5 25",
    "imageUrl": "https://tcgplayer-cdn.tcgplayer.com/product/232320_200w.jpg",
    "categoryId": 3,
    "groupId": 2782,
    "url": "https://www.tcgplayer.com/product/232320/pokemon-mcdonalds-25th-anniversary-promos-snivy-5-25",
    "modifiedOn": "2022-09-23T16:41:30.897",
    "imageCount": 1,
    "presaleInfo": {
      "isPresale": false,
      "releasedOn": null,
      "note": null
    },
    "extendedData": [
      {
        "name": "Number",
        "displayName": "Card Number",
        "value": "005/025"
      },
      {
        "name": "Rarity",
        "displayName": "Rarity",
        "value": "Promo"
      },
      {
        "name": "Card Type",
        "displayName": "Card Type",
        "value": "Grass"
      },
      {
        "name": "HP",
        "displayName": "HP",
        "value": "60"
      },
      {
        "name": "Stage",
        "displayName": "Stage",
        "value": "Basic"
      },
      {
        "name": "Attack 1",
        "displayName": "Attack 1",
        "value": "[1G] Slam (20x)\r\n<br>Flip 2 coins. This attack does 20 damage times the number of heads."
      },
      {
        "name": "Weakness",
        "displayName": "Weakness",
        "value": "Rx2"
      },
      {
        "name": "Resistance",
        "displayName": "Resistance",
        "value": "W-20"
      },
      {
        "name": "RetreatCost",
        "displayName": "Retreat Cost",
        "value": "1"
      }
    ],
    "prices": [
      {
        "subTypeName": "Normal",
        "lowPrice": 0.15,
        "midPrice": 0.33,
        "highPrice": 190637.15,
        "marketPrice": 0.31,
        "directLowPrice": null
      },
      {
        "subTypeName": "Holofoil",
        "lowPrice": 0.25,
        "midPrice": 1,
        "highPrice": 5,
        "marketPrice": 0.84,
        "directLowPrice": null
      }
    ]
  },
  {
    "productId": 232321,
    "name": "Chespin - 6/25",
    "cleanName": "Chespin 6 25",
    "imageUrl": "https://tcgplayer-cdn.tcgplayer.com/product/232321_200w.jpg",
    "categoryId": 3,
    "groupId": 2782,
    "url": "https://www.tcgplayer.com/product/232321/pokemon-mcdonalds-25th-anniversary-promos-chespin-6-25",
    "modifiedOn": "2022-09-23T16:23:25.187",
    "imageCount": 1,
    "presaleInfo": {
      "isPresale": false,
      "releasedOn": null,
      "note": null
    },
    "extendedData": [
      {
        "name": "Number",
        "displayName": "Card Number",
        "value": "006/025"
      },
      {
        "name": "Rarity",
        "displayName": "Rarity",
        "value": "Promo"
      },
      {
        "name": "Card Type",
        "displayName": "Card Type",
        "value": "Grass"
      },
      {
        "name": "HP",
        "displayName": "HP",
        "value": "60"
      },
      {
        "name": "Stage",
        "displayName": "Stage",
        "value": "Basic"
      },
      {
        "name": "Attack 1",
        "displayName": "Attack 1",
        "value": "[G] Vine Whip (10)"
      },
      {
        "name": "Attack 2",
        "displayName": "Attack 2",
        "value": "[1G] Seed Bomb (20)"
      },
      {
        "name": "Weakness",
        "displayName": "Weakness",
        "value": "Rx2"
      },
      {
        "name": "RetreatCost",
        "displayName": "Retreat Cost",
        "value": "1"
      }
    ],
    "prices": [
      {
        "subTypeName": "Normal",
        "lowPrice": 0.1,
        "midPrice": 0.3,
        "highPrice": 58.32,
        "marketPrice": 0.23,
        "directLowPrice": null
      },
      {
        "subTypeName": "Holofoil",
        "lowPrice": 0.25,
        "midPrice": 0.75,
        "highPrice": 5,
        "marketPrice": 0.56,
        "directLowPrice": null
      }
    ]
  },
  {
    "productId": 232322,
    "name": "Rowlet - 7/25",
    "cleanName": "Rowlet 7 25",
    "imageUrl": "https://tcgplayer-cdn.tcgplayer.com/product/232322_200w.jpg",
    "categoryId": 3,
    "groupId": 2782,
    "url": "https://www.tcgplayer.com/product/232322/pokemon-mcdonalds-25th-anniversary-promos-rowlet-7-25",
    "modifiedOn": "2022-09-23T16:38:41.907",
    "imageCount": 1,
    "presaleInfo": {
      "isPresale": false,
      "releasedOn": null,
      "note": null
    },
    "extendedData": [
      {
        "name": "Number",
        "displayName": "Card Number",
        "value": "007/025"
      },
      {
        "name": "Rarity",
        "displayName": "Rarity",
        "value": "Promo"
      },
      {
        "name": "Card Type",
        "displayName": "Card Type",
        "value": "Grass"
      },
      {
        "name": "HP",
        "displayName": "HP",
        "value": "60"
      },
      {
        "name": "Stage",
        "displayName": "Stage",
        "value": "Basic"
      },
      {
        "name": "Attack 1",
        "displayName": "Attack 1",
        "value": "[1] Tackle (10)"
      },
      {
        "name": "Attack 2",
        "displayName": "Attack 2",
        "value": "[1G] Leafage (20)"
      },
      {
        "name": "Weakness",
        "displayName": "Weakness",
        "value": "Rx2"
      },
      {
        "name": "RetreatCost",
        "displayName": "Retreat Cost",
        "value": "1"
      }
    ],
    "prices": [
      {
        "subTypeName": "Holofoil",
        "lowPrice": 0.44,
        "midPrice": 1.05,
        "highPrice": 5,
        "marketPrice": 0.88,
        "directLowPrice": null
      },
      {
        "subTypeName": "Normal",
        "lowPrice": 0.05,
        "midPrice": 0.33,
        "highPrice": 152933.27,
        "marketPrice": 0.31,
        "directLowPrice": null
      }
    ]
  },
  {
    "productId": 232323,
    "name": "Grookey - 8/25",
    "cleanName": "Grookey 8 25",
    "imageUrl": "https://tcgplayer-cdn.tcgplayer.com/product/232323_200w.jpg",
    "categoryId": 3,
    "groupId": 2782,
    "url": "https://www.tcgplayer.com/product/232323/pokemon-mcdonalds-25th-anniversary-promos-grookey-8-25",
    "modifiedOn": "2022-09-23T16:29:54.56",
    "imageCount": 1,
    "presaleInfo": {
      "isPresale": false,
      "releasedOn": null,
      "note": null
    },
    "extendedData": [
      {
        "name": "Number",
        "displayName": "Card Number",
        "value": "008/025"
      },
      {
        "name": "Rarity",
        "displayName": "Rarity",
        "value": "Promo"
      },
      {
        "name": "Card Type",
        "displayName": "Card Type",
        "value": "Grass"
      },
      {
        "name": "HP",
        "displayName": "HP",
        "value": "60"
      },
      {
        "name": "Stage",
        "displayName": "Stage",
        "value": "Basic"
      },
      {
        "name": "Attack 1",
        "displayName": "Attack 1",
        "value": "[1G] Branch Poke (30)"
      },
      {
        "name": "Weakness",
        "displayName": "Weakness",
        "value": "Rx2"
      },
      {
        "name": "RetreatCost",
        "displayName": "Retreat Cost",
        "value": "1"
      }
    ],
    "prices": [
      {
        "subTypeName": "Holofoil",
        "lowPrice": 0.45,
        "midPrice": 0.93,
        "highPrice": 55,
        "marketPrice": 0.54,
        "directLowPrice": 0.76
      },
      {
        "subTypeName": "Normal",
        "lowPrice": 0.08,
        "midPrice": 0.26,
        "highPrice": 190635.31,
        "marketPrice": 0.25,
        "directLowPrice": 0.24
      }
    ]
  },
  {
    "productId": 232324,
    "name": "Charmander - 9/25",
    "cleanName": "Charmander 9 25",
    "imageUrl": "https://tcgplayer-cdn.tcgplayer.com/product/232324_200w.jpg",
    "categoryId": 3,
    "groupId": 2782,
    "url": "https://www.tcgplayer.com/product/232324/pokemon-mcdonalds-25th-anniversary-promos-charmander-9-25",
    "modifiedOn": "2022-09-23T16:20:23.007",
    "imageCount": 1,
    "presaleInfo": {
      "isPresale": false,
      "releasedOn": null,
      "note": null
    },
    "extendedData": [
      {
        "name": "Number",
        "displayName": "Card Number",
        "value": "009/025"
      },
      {
        "name": "Rarity",
        "displayName": "Rarity",
        "value": "Promo"
      },
      {
        "name": "Card Type",
        "displayName": "Card Type",
        "value": "Fire"
      },
      {
        "name": "HP",
        "displayName": "HP",
        "value": "70"
      },
      {
        "name": "Stage",
        "displayName": "Stage",
        "value": "Basic"
      },
      {
        "name": "Attack 1",
        "displayName": "Attack 1",
        "value": "[1] Scratch (10)"
      },
      {
        "name": "Attack 2",
        "displayName": "Attack 2",
        "value": "[1R] Flame Tail (20)"
      },
      {
        "name": "Weakness",
        "displayName": "Weakness",
        "value": "Wx2"
      },
      {
        "name": "RetreatCost",
        "displayName": "Retreat Cost",
        "value": "1"
      }
    ],
    "prices": [
      {
        "subTypeName": "Holofoil",
        "lowPrice": 0.99,
        "midPrice": 3,
        "highPrice": 32,
        "marketPrice": 3.07,
        "directLowPrice": 4.99
      },
      {
        "subTypeName": "Normal",
        "lowPrice": 0.18,
        "midPrice": 0.5,
        "highPrice": 172581.03,
        "marketPrice": 0.41,
        "directLowPrice": null
      }
    ]
  },
  {
    "productId": 232325,
    "name": "Cyndaquil - 10/25",
    "cleanName": "Cyndaquil 10 25",
    "imageUrl": "https://tcgplayer-cdn.tcgplayer.com/product/232325_200w.jpg",
    "categoryId": 3,
    "groupId": 2782,
    "url": "https://www.tcgplayer.com/product/232325/pokemon-mcdonalds-25th-anniversary-promos-cyndaquil-10-25",
    "modifiedOn": "2022-11-15T16:46:58.257",
    "imageCount": 1,
    "presaleInfo": {
      "isPresale": false,
      "releasedOn": null,
      "note": null
    },
    "extendedData": [
      {
        "name": "Number",
        "displayName": "Card Number",
        "value": "010/025"
      },
      {
        "name": "Rarity",
        "displayName": "Rarity",
        "value": "Promo"
      },
      {
        "name": "Card Type",
        "displayName": "Card Type",
        "value": "Fire"
      },
      {
        "name": "HP",
        "displayName": "HP",
        "value": "70"
      },
      {
        "name": "Stage",
        "displayName": "Stage",
        "value": "Basic"
      },
      {
        "name": "Attack 1",
        "displayName": "Attack 1",
        "value": "[2] Hammer In (30)"
      },
      {
        "name": "Weakness",
        "displayName": "Weakness",
        "value": "Wx2"
      },
      {
        "name": "RetreatCost",
        "displayName": "Retreat Cost",
        "value": "1"
      }
    ],
    "prices": [
      {
        "subTypeName": "Holofoil",
        "lowPrice": 0.55,
        "midPrice": 1.31,
        "highPrice": 6.99,
        "marketPrice": 0.78,
        "directLowPrice": null
      },
      {
        "subTypeName": "Normal",
        "lowPrice": 0.15,
        "midPrice": 0.33,
        "highPrice": 68.4,
        "marketPrice": 0.3,
        "directLowPrice": 0.25
      }
    ]
  },
  {
    "productId": 232326,
    "name": "Torchic - 11/25",
    "cleanName": "Torchic 11 25",
    "imageUrl": "https://tcgplayer-cdn.tcgplayer.com/product/232326_200w.jpg",
    "categoryId": 3,
    "groupId": 2782,
    "url": "https://www.tcgplayer.com/product/232326/pokemon-mcdonalds-25th-anniversary-promos-torchic-11-25",
    "modifiedOn": "2024-08-12T20:08:05.177",
    "imageCount": 1,
    "presaleInfo": {
      "isPresale": false,
      "releasedOn": null,
      "note": null
    },
    "extendedData": [
      {
        "name": "Number",
        "displayName": "Card Number",
        "value": "011/025"
      },
      {
        "name": "Rarity",
        "displayName": "Rarity",
        "value": "Promo"
      },
      {
        "name": "Card Type",
        "displayName": "Card Type",
        "value": "Fire"
      },
      {
        "name": "HP",
        "displayName": "HP",
        "value": "60"
      },
      {
        "name": "Stage",
        "displayName": "Stage",
        "value": "Basic"
      },
      {
        "name": "Attack 1",
        "displayName": "Attack 1",
        "value": "[R] Ember (20)\r\n<br> Flip a coin. If tails, discard a Fire Energy attached to this Pokémon."
      },
      {
        "name": "Weakness",
        "displayName": "Weakness",
        "value": "Wx2"
      },
      {
        "name": "RetreatCost",
        "displayName": "Retreat Cost",
        "value": "1"
      }
    ],
    "prices": [
      {
        "subTypeName": "Holofoil",
        "lowPrice": 0.25,
        "midPrice": 1.04,
        "highPrice": 5,
        "marketPrice": 0.88,
        "directLowPrice": null
      },
      {
        "subTypeName": "Normal",
        "lowPrice": 0.15,
        "midPrice": 0.38,
        "highPrice": 143945.91,
        "marketPrice": 0.36,
        "directLowPrice": null
      }
    ]
  },
  {
    "productId": 232327,
    "name": "Chimchar - 12/25",
    "cleanName": "Chimchar 12 25",
    "imageUrl": "https://tcgplayer-cdn.tcgplayer.com/product/232327_200w.jpg",
    "categoryId": 3,
    "groupId": 2782,
    "url": "https://www.tcgplayer.com/product/232327/pokemon-mcdonalds-25th-anniversary-promos-chimchar-12-25",
    "modifiedOn": "2024-09-03T21:42:02.563",
    "imageCount": 1,
    "presaleInfo": {
      "isPresale": false,
      "releasedOn": null,
      "note": null
    },
    "extendedData": [
      {
        "name": "Number",
        "displayName": "Card Number",
        "value": "012/025"
      },
      {
        "name": "Rarity",
        "displayName": "Rarity",
        "value": "Promo"
      },
      {
        "name": "Card Type",
        "displayName": "Card Type",
        "value": "Fire"
      },
      {
        "name": "HP",
        "displayName": "HP",
        "value": "60"
      },
      {
        "name": "Stage",
        "displayName": "Stage",
        "value": "Basic"
      },
      {
        "name": "Attack 1",
        "displayName": "Attack 1",
        "value": "[1] Fury Swipes (10x)\r\n<br>Flip 3 coins. This attack does 10 damage for each heads."
      },
      {
        "name": "Weakness",
        "displayName": "Weakness",
        "value": "Wx2"
      },
      {
        "name": "RetreatCost",
        "displayName": "Retreat Cost",
        "value": "1"
      }
    ],
    "prices": [
      {
        "subTypeName": "Holofoil",
        "lowPrice": 0.3,
        "midPrice": 1,
        "highPrice": 3.29,
        "marketPrice": 0.84,
        "directLowPrice": null
      },
      {
        "subTypeName": "Normal",
        "lowPrice": 0.2,
        "midPrice": 0.33,
        "highPrice": 5,
        "marketPrice": 0.31,
        "directLowPrice": 0.25
      }
    ]
  },
  {
    "productId": 232328,
    "name": "Tepig - 13/25",
    "cleanName": "Tepig 13 25",
    "imageUrl": "https://tcgplayer-cdn.tcgplayer.com/product/232328_200w.jpg",
    "categoryId": 3,
    "groupId": 2782,
    "url": "https://www.tcgplayer.com/product/232328/pokemon-mcdonalds-25th-anniversary-promos-tepig-13-25",
    "modifiedOn": "2023-06-01T19:40:21.103",
    "imageCount": 1,
    "presaleInfo": {
      "isPresale": false,
      "releasedOn": null,
      "note": null
    },
    "extendedData": [
      {
        "name": "Number",
        "displayName": "Card Number",
        "value": "013/025"
      },
      {
        "name": "Rarity",
        "displayName": "Rarity",
        "value": "Promo"
      },
      {
        "name": "Card Type",
        "displayName": "Card Type",
        "value": "Fire"
      },
      {
        "name": "HP",
        "displayName": "HP",
        "value": "70"
      },
      {
        "name": "Stage",
        "displayName": "Stage",
        "value": "Basic"
      },
      {
        "name": "Attack 1",
        "displayName": "Attack 1",
        "value": "[1R] Ember (30)\r\n<br>Discard an Energy attached to this Pokémon."
      },
      {
        "name": "Weakness",
        "displayName": "Weakness",
        "value": "Wx2"
      },
      {
        "name": "RetreatCost",
        "displayName": "Retreat Cost",
        "value": "2"
      }
    ],
    "prices": [
      {
        "subTypeName": "Normal",
        "lowPrice": 0.06,
        "midPrice": 0.26,
        "highPrice": 5,
        "marketPrice": 0.24,
        "directLowPrice": 0.22
      },
      {
        "subTypeName": "Holofoil",
        "lowPrice": 0.23,
        "midPrice": 1,
        "highPrice": 5,
        "marketPrice": 0.72,
        "directLowPrice": null
      }
    ]
  },
  {
    "productId": 232329,
    "name": "Fennekin - 14/25",
    "cleanName": "Fennekin 14 25",
    "imageUrl": "https://tcgplayer-cdn.tcgplayer.com/product/232329_200w.jpg",
    "categoryId": 3,
    "groupId": 2782,
    "url": "https://www.tcgplayer.com/product/232329/pokemon-mcdonalds-25th-anniversary-promos-fennekin-14-25",
    "modifiedOn": "2022-09-23T16:27:16.287",
    "imageCount": 1,
    "presaleInfo": {
      "isPresale": false,
      "releasedOn": null,
      "note": null
    },
    "extendedData": [
      {
        "name": "Number",
        "displayName": "Card Number",
        "value": "014/025"
      },
      {
        "name": "Rarity",
        "displayName": "Rarity",
        "value": "Promo"
      },
      {
        "name": "Card Type",
        "displayName": "Card Type",
        "value": "Fire"
      },
      {
        "name": "HP",
        "displayName": "HP",
        "value": "60"
      },
      {
        "name": "Stage",
        "displayName": "Stage",
        "value": "Basic"
      },
      {
        "name": "Attack 1",
        "displayName": "Attack 1",
        "value": "[R] Scratch (10)"
      },
      {
        "name": "Attack 2",
        "displayName": "Attack 2",
        "value": "[1R] Live Coal (20)"
      },
      {
        "name": "Weakness",
        "displayName": "Weakness",
        "value": "Wx2"
      },
      {
        "name": "RetreatCost",
        "displayName": "Retreat Cost",
        "value": "1"
      }
    ],
    "prices": [
      {
        "subTypeName": "Holofoil",
        "lowPrice": 0.23,
        "midPrice": 0.99,
        "highPrice": 53,
        "marketPrice": 0.78,
        "directLowPrice": null
      },
      {
        "subTypeName": "Normal",
        "lowPrice": 0.14,
        "midPrice": 0.26,
        "highPrice": 2,
        "marketPrice": 0.24,
        "directLowPrice": null
      }
    ]
  },
  {
    "productId": 232330,
    "name": "Scorbunny - 16/25",
    "cleanName": "Scorbunny 16 25",
    "imageUrl": "https://tcgplayer-cdn.tcgplayer.com/product/232330_200w.jpg",
    "categoryId": 3,
    "groupId": 2782,
    "url": "https://www.tcgplayer.com/product/232330/pokemon-mcdonalds-25th-anniversary-promos-scorbunny-16-25",
    "modifiedOn": "2025-06-07T04:11:03.34",
    "imageCount": 1,
    "presaleInfo": {
      "isPresale": false,
      "releasedOn": null,
      "note": null
    },
    "extendedData": [
      {
        "name": "Number",
        "displayName": "Card Number",
        "value": "016/025"
      },
      {
        "name": "Rarity",
        "displayName": "Rarity",
        "value": "Promo"
      },
      {
        "name": "Card Type",
        "displayName": "Card Type",
        "value": "Fire"
      },
      {
        "name": "HP",
        "displayName": "HP",
        "value": "60"
      },
      {
        "name": "Stage",
        "displayName": "Stage",
        "value": "Basic"
      },
      {
        "name": "Attack 1",
        "displayName": "Attack 1",
        "value": "[R] Super Singe (10)\r\n<br>Flip a coin. If heads, your opponent's Active Pokémon is now Burned."
      },
      {
        "name": "Weakness",
        "displayName": "Weakness",
        "value": "Wx2"
      },
      {
        "name": "RetreatCost",
        "displayName": "Retreat Cost",
        "value": "1"
      }
    ],
    "prices": [
      {
        "subTypeName": "Normal",
        "lowPrice": 0.1,
        "midPrice": 0.28,
        "highPrice": 192787.69,
        "marketPrice": 0.23,
        "directLowPrice": null
      },
      {
        "subTypeName": "Holofoil",
        "lowPrice": 0.25,
        "midPrice": 1.25,
        "highPrice": 5,
        "marketPrice": 1.03,
        "directLowPrice": 1.19
      }
    ]
  },
  {
    "productId": 232331,
    "name": "Squirtle - 17/25",
    "cleanName": "Squirtle 17 25",
    "imageUrl": "https://tcgplayer-cdn.tcgplayer.com/product/232331_200w.jpg",
    "categoryId": 3,
    "groupId": 2782,
    "url": "https://www.tcgplayer.com/product/232331/pokemon-mcdonalds-25th-anniversary-promos-squirtle-17-25",
    "modifiedOn": "2022-09-23T16:43:22.447",
    "imageCount": 1,
    "presaleInfo": {
      "isPresale": false,
      "releasedOn": null,
      "note": null
    },
    "extendedData": [
      {
        "name": "Number",
        "displayName": "Card Number",
        "value": "017/025"
      },
      {
        "name": "Rarity",
        "displayName": "Rarity",
        "value": "Promo"
      },
      {
        "name": "Card Type",
        "displayName": "Card Type",
        "value": "Water"
      },
      {
        "name": "HP",
        "displayName": "HP",
        "value": "60"
      },
      {
        "name": "Stage",
        "displayName": "Stage",
        "value": "Basic"
      },
      {
        "name": "Attack 1",
        "displayName": "Attack 1",
        "value": "[W] Bubble (10)\r\n<br>Flip a coin. If heads, your opponent's Active Pokémon is now Paralyzed."
      },
      {
        "name": "Weakness",
        "displayName": "Weakness",
        "value": "Gx2"
      },
      {
        "name": "RetreatCost",
        "displayName": "Retreat Cost",
        "value": "1"
      }
    ],
    "prices": [
      {
        "subTypeName": "Holofoil",
        "lowPrice": 1.79,
        "midPrice": 3.47,
        "highPrice": 20,
        "marketPrice": 2.62,
        "directLowPrice": 3.75
      },
      {
        "subTypeName": "Normal",
        "lowPrice": 0.1,
        "midPrice": 0.67,
        "highPrice": 20,
        "marketPrice": 0.61,
        "directLowPrice": null
      }
    ]
  },
  {
    "productId": 232332,
    "name": "Totodile - 18/25",
    "cleanName": "Totodile 18 25",
    "imageUrl": "https://tcgplayer-cdn.tcgplayer.com/product/232332_200w.jpg",
    "categoryId": 3,
    "groupId": 2782,
    "url": "https://www.tcgplayer.com/product/232332/pokemon-mcdonalds-25th-anniversary-promos-totodile-18-25",
    "modifiedOn": "2024-10-18T12:21:09.813",
    "imageCount": 1,
    "presaleInfo": {
      "isPresale": false,
      "releasedOn": null,
      "note": null
    },
    "extendedData": [
      {
        "name": "Number",
        "displayName": "Card Number",
        "value": "018/025"
      },
      {
        "name": "Rarity",
        "displayName": "Rarity",
        "value": "Promo"
      },
      {
        "name": "Card Type",
        "displayName": "Card Type",
        "value": "Water"
      },
      {
        "name": "HP",
        "displayName": "HP",
        "value": "60"
      },
      {
        "name": "Stage",
        "displayName": "Stage",
        "value": "Basic"
      },
      {
        "name": "Attack 1",
        "displayName": "Attack 1",
        "value": "[W] Fury Strikes (10x)\r\n<br>Flip 3 coins. This attack does 10 damage times the number of heads."
      },
      {
        "name": "Weakness",
        "displayName": "Weakness",
        "value": "Gx2"
      },
      {
        "name": "RetreatCost",
        "displayName": "Retreat Cost",
        "value": "1"
      }
    ],
    "prices": [
      {
        "subTypeName": "Normal",
        "lowPrice": 0.15,
        "midPrice": 0.38,
        "highPrice": 19,
        "marketPrice": 0.36,
        "directLowPrice": null
      },
      {
        "subTypeName": "Holofoil",
        "lowPrice": 0.5,
        "midPrice": 2,
        "highPrice": 5.97,
        "marketPrice": 1.98,
        "directLowPrice": 2.8
      }
    ]
  },
  {
    "productId": 232333,
    "name": "Mudkip - 19/25",
    "cleanName": "Mudkip 19 25",
    "imageUrl": "https://tcgplayer-cdn.tcgplayer.com/product/232333_200w.jpg",
    "categoryId": 3,
    "groupId": 2782,
    "url": "https://www.tcgplayer.com/product/232333/pokemon-mcdonalds-25th-anniversary-promos-mudkip-19-25",
    "modifiedOn": "2023-10-20T21:09:19.14",
    "imageCount": 1,
    "presaleInfo": {
      "isPresale": false,
      "releasedOn": null,
      "note": null
    },
    "extendedData": [
      {
        "name": "Number",
        "displayName": "Card Number",
        "value": "019/025"
      },
      {
        "name": "Rarity",
        "displayName": "Rarity",
        "value": "Promo"
      },
      {
        "name": "Card Type",
        "displayName": "Card Type",
        "value": "Water"
      },
      {
        "name": "HP",
        "displayName": "HP",
        "value": "60"
      },
      {
        "name": "Stage",
        "displayName": "Stage",
        "value": "Basic"
      },
      {
        "name": "Attack 1",
        "displayName": "Attack 1",
        "value": "[W] Tackle (10)"
      },
      {
        "name": "Attack 2",
        "displayName": "Attack 2",
        "value": "[1W] Mud Slap (20)"
      },
      {
        "name": "Weakness",
        "displayName": "Weakness",
        "value": "Gx2"
      },
      {
        "name": "RetreatCost",
        "displayName": "Retreat Cost",
        "value": "1"
      }
    ],
    "prices": [
      {
        "subTypeName": "Holofoil",
        "lowPrice": 0.27,
        "midPrice": 1.65,
        "highPrice": 5,
        "marketPrice": 1.53,
        "directLowPrice": 1.72
      },
      {
        "subTypeName": "Normal",
        "lowPrice": 0.1,
        "midPrice": 0.4,
        "highPrice": 4.39,
        "marketPrice": 0.33,
        "directLowPrice": 0.4
      }
    ]
  },
  {
    "productId": 232334,
    "name": "Piplup - 20/25",
    "cleanName": "Piplup 20 25",
    "imageUrl": "https://tcgplayer-cdn.tcgplayer.com/product/232334_200w.jpg",
    "categoryId": 3,
    "groupId": 2782,
    "url": "https://www.tcgplayer.com/product/232334/pokemon-mcdonalds-25th-anniversary-promos-piplup-20-25",
    "modifiedOn": "2025-05-21T10:41:18.067",
    "imageCount": 1,
    "presaleInfo": {
      "isPresale": false,
      "releasedOn": null,
      "note": null
    },
    "extendedData": [
      {
        "name": "Number",
        "displayName": "Card Number",
        "value": "020/025"
      },
      {
        "name": "Rarity",
        "displayName": "Rarity",
        "value": "Promo"
      },
      {
        "name": "Card Type",
        "displayName": "Card Type",
        "value": "Water"
      },
      {
        "name": "HP",
        "displayName": "HP",
        "value": "70"
      },
      {
        "name": "Stage",
        "displayName": "Stage",
        "value": "Basic"
      },
      {
        "name": "Attack 1",
        "displayName": "Attack 1",
        "value": "[1] Peck (10)"
      },
      {
        "name": "Attack 2",
        "displayName": "Attack 2",
        "value": "[1W] Wave Splash (20)"
      },
      {
        "name": "Weakness",
        "displayName": "Weakness",
        "value": "Lx2"
      },
      {
        "name": "RetreatCost",
        "displayName": "Retreat Cost",
        "value": "1"
      }
    ],
    "prices": [
      {
        "subTypeName": "Normal",
        "lowPrice": 0.15,
        "midPrice": 0.4,
        "highPrice": 2,
        "marketPrice": 0.38,
        "directLowPrice": null
      },
      {
        "subTypeName": "Holofoil",
        "lowPrice": 0.91,
        "midPrice": 2.32,
        "highPrice": 89,
        "marketPrice": 2.3,
        "directLowPrice": 2.31
      }
    ]
  },
  {
    "productId": 232335,
    "name": "Oshawott - 21/25",
    "cleanName": "Oshawott 21 25",
    "imageUrl": "https://tcgplayer-cdn.tcgplayer.com/product/232335_200w.jpg",
    "categoryId": 3,
    "groupId": 2782,
    "url": "https://www.tcgplayer.com/product/232335/pokemon-mcdonalds-25th-anniversary-promos-oshawott-21-25",
    "modifiedOn": "2022-09-23T16:33:51.813",
    "imageCount": 1,
    "presaleInfo": {
      "isPresale": false,
      "releasedOn": null,
      "note": null
    },
    "extendedData": [
      {
        "name": "Number",
        "displayName": "Card Number",
        "value": "021/025"
      },
      {
        "name": "Rarity",
        "displayName": "Rarity",
        "value": "Promo"
      },
      {
        "name": "Card Type",
        "displayName": "Card Type",
        "value": "Water"
      },
      {
        "name": "HP",
        "displayName": "HP",
        "value": "60"
      },
      {
        "name": "Stage",
        "displayName": "Stage",
        "value": "Basic"
      },
      {
        "name": "Attack 1",
        "displayName": "Attack 1",
        "value": "[1W] Water Pulse (20)\r\n<br>Flip a coin. If heads, the Defending Pokémon is now Asleep."
      },
      {
        "name": "Weakness",
        "displayName": "Weakness",
        "value": "Lx2"
      },
      {
        "name": "RetreatCost",
        "displayName": "Retreat Cost",
        "value": "1"
      }
    ],
    "prices": [
      {
        "subTypeName": "Normal",
        "lowPrice": 0.1,
        "midPrice": 0.31,
        "highPrice": 2,
        "marketPrice": 0.25,
        "directLowPrice": null
      },
      {
        "subTypeName": "Holofoil",
        "lowPrice": 0.37,
        "midPrice": 1,
        "highPrice": 3.11,
        "marketPrice": 0.84,
        "directLowPrice": null
      }
    ]
  },
  {
    "productId": 232336,
    "name": "Froakie - 22/25",
    "cleanName": "Froakie 22 25",
    "imageUrl": "https://tcgplayer-cdn.tcgplayer.com/product/232336_200w.jpg",
    "categoryId": 3,
    "groupId": 2782,
    "url": "https://www.tcgplayer.com/product/232336/pokemon-mcdonalds-25th-anniversary-promos-froakie-22-25",
    "modifiedOn": "2024-05-26T12:05:01.497",
    "imageCount": 1,
    "presaleInfo": {
      "isPresale": false,
      "releasedOn": null,
      "note": null
    },
    "extendedData": [
      {
        "name": "Number",
        "displayName": "Card Number",
        "value": "022/025"
      },
      {
        "name": "Rarity",
        "displayName": "Rarity",
        "value": "Promo"
      },
      {
        "name": "Card Type",
        "displayName": "Card Type",
        "value": "Water"
      },
      {
        "name": "HP",
        "displayName": "HP",
        "value": "60"
      },
      {
        "name": "Stage",
        "displayName": "Stage",
        "value": "Basic"
      },
      {
        "name": "Attack 1",
        "displayName": "Attack 1",
        "value": "[W] Pound (10)"
      },
      {
        "name": "Attack 2",
        "displayName": "Attack 2",
        "value": "[1W] Water Drip (20)"
      },
      {
        "name": "Weakness",
        "displayName": "Weakness",
        "value": "Gx2"
      },
      {
        "name": "RetreatCost",
        "displayName": "Retreat Cost",
        "value": "1"
      }
    ],
    "prices": [
      {
        "subTypeName": "Normal",
        "lowPrice": 0.05,
        "midPrice": 0.26,
        "highPrice": 173839.15,
        "marketPrice": 0.27,
        "directLowPrice": null
      },
      {
        "subTypeName": "Holofoil",
        "lowPrice": 0.4,
        "midPrice": 1.28,
        "highPrice": 3.99,
        "marketPrice": 1.21,
        "directLowPrice": 2.49
      }
    ]
  },
  {
    "productId": 232337,
    "name": "Popplio - 23/25",
    "cleanName": "Popplio 23 25",
    "imageUrl": "https://tcgplayer-cdn.tcgplayer.com/product/232337_200w.jpg",
    "categoryId": 3,
    "groupId": 2782,
    "url": "https://www.tcgplayer.com/product/232337/pokemon-mcdonalds-25th-anniversary-promos-popplio-23-25",
    "modifiedOn": "2022-09-23T16:37:30.89",
    "imageCount": 1,
    "presaleInfo": {
      "isPresale": false,
      "releasedOn": null,
      "note": null
    },
    "extendedData": [
      {
        "name": "Number",
        "displayName": "Card Number",
        "value": "023/025"
      },
      {
        "name": "Rarity",
        "displayName": "Rarity",
        "value": "Promo"
      },
      {
        "name": "Card Type",
        "displayName": "Card Type",
        "value": "Water"
      },
      {
        "name": "HP",
        "displayName": "HP",
        "value": "70"
      },
      {
        "name": "Stage",
        "displayName": "Stage",
        "value": "Basic"
      },
      {
        "name": "Attack 1",
        "displayName": "Attack 1",
        "value": "[W] Pound (10)"
      },
      {
        "name": "Attack 2",
        "displayName": "Attack 2",
        "value": "[1W] Water Gun (20)"
      },
      {
        "name": "Weakness",
        "displayName": "Weakness",
        "value": "Gx2"
      },
      {
        "name": "RetreatCost",
        "displayName": "Retreat Cost",
        "value": "1"
      }
    ],
    "prices": [
      {
        "subTypeName": "Normal",
        "lowPrice": 0.09,
        "midPrice": 0.28,
        "highPrice": 5,
        "marketPrice": 0.25,
        "directLowPrice": null
      },
      {
        "subTypeName": "Holofoil",
        "lowPrice": 1,
        "midPrice": 1.99,
        "highPrice": 8.36,
        "marketPrice": 1.66,
        "directLowPrice": null
      }
    ]
  },
  {
    "productId": 232338,
    "name": "Sobble - 24/25",
    "cleanName": "Sobble 24 25",
    "imageUrl": "https://tcgplayer-cdn.tcgplayer.com/product/232338_200w.jpg",
    "categoryId": 3,
    "groupId": 2782,
    "url": "https://www.tcgplayer.com/product/232338/pokemon-mcdonalds-25th-anniversary-promos-sobble-24-25",
    "modifiedOn": "2022-12-17T21:28:41.037",
    "imageCount": 1,
    "presaleInfo": {
      "isPresale": false,
      "releasedOn": null,
      "note": null
    },
    "extendedData": [
      {
        "name": "Number",
        "displayName": "Card Number",
        "value": "024/025"
      },
      {
        "name": "Rarity",
        "displayName": "Rarity",
        "value": "Promo"
      },
      {
        "name": "Card Type",
        "displayName": "Card Type",
        "value": "Water"
      },
      {
        "name": "HP",
        "displayName": "HP",
        "value": "60"
      },
      {
        "name": "Stage",
        "displayName": "Stage",
        "value": "Basic"
      },
      {
        "name": "Attack 1",
        "displayName": "Attack 1",
        "value": "[1W] Bind (20)\r\n<br>Flip a coin. If heads, your opponent's Active Pokémon is now Paralyzed."
      },
      {
        "name": "Weakness",
        "displayName": "Weakness",
        "value": "Lx2"
      },
      {
        "name": "RetreatCost",
        "displayName": "Retreat Cost",
        "value": "1"
      }
    ],
    "prices": [
      {
        "subTypeName": "Holofoil",
        "lowPrice": 1.25,
        "midPrice": 3.23,
        "highPrice": 7.99,
        "marketPrice": 2.79,
        "directLowPrice": 4.99
      },
      {
        "subTypeName": "Normal",
        "lowPrice": 0.06,
        "midPrice": 0.3,
        "highPrice": 25389.36,
        "marketPrice": 0.24,
        "directLowPrice": null
      }
    ]
  },
  {
    "productId": 232339,
    "name": "Pikachu - 25/25",
    "cleanName": "Pikachu 25 25",
    "imageUrl": "https://tcgplayer-cdn.tcgplayer.com/product/232339_200w.jpg",
    "categoryId": 3,
    "groupId": 2782,
    "url": "https://www.tcgplayer.com/product/232339/pokemon-mcdonalds-25th-anniversary-promos-pikachu-25-25",
    "modifiedOn": "2025-03-10T05:51:05.377",
    "imageCount": 1,
    "presaleInfo": {
      "isPresale": false,
      "releasedOn": null,
      "note": null
    },
    "extendedData": [
      {
        "name": "Number",
        "displayName": "Card Number",
        "value": "025/025"
      },
      {
        "name": "Rarity",
        "displayName": "Rarity",
        "value": "Promo"
      },
      {
        "name": "Card Type",
        "displayName": "Card Type",
        "value": "Lightning"
      },
      {
        "name": "HP",
        "displayName": "HP",
        "value": "60"
      },
      {
        "name": "Stage",
        "displayName": "Stage",
        "value": "Basic"
      },
      {
        "name": "Attack 1",
        "displayName": "Attack 1",
        "value": "[L] Meal Time\r\n<br>Flip a coin until you get tails. For each heads, draw a card."
      },
      {
        "name": "Attack 2",
        "displayName": "Attack 2",
        "value": "[1L] Gnaw (20)"
      },
      {
        "name": "Weakness",
        "displayName": "Weakness",
        "value": "Fx2"
      },
      {
        "name": "Resistance",
        "displayName": "Resistance",
        "value": "M-20"
      },
      {
        "name": "RetreatCost",
        "displayName": "Retreat Cost",
        "value": "1"
      }
    ],
    "prices": [
      {
        "subTypeName": "Normal",
        "lowPrice": 0.39,
        "midPrice": 1.25,
        "highPrice": 79716.24,
        "marketPrice": 1.24,
        "directLowPrice": 1.26
      },
      {
        "subTypeName": "Holofoil",
        "lowPrice": 8,
        "midPrice": 11.96,
        "highPrice": 29.99,
        "marketPrice": 10.24,
        "directLowPrice": 8.87
      }
    ]
  },
  {
    "productId": 232341,
    "name": "Litten - 15/25",
    "cleanName": "Litten 15 25",
    "imageUrl": "https://tcgplayer-cdn.tcgplayer.com/product/232341_200w.jpg",
    "categoryId": 3,
    "groupId": 2782,
    "url": "https://www.tcgplayer.com/product/232341/pokemon-mcdonalds-25th-anniversary-promos-litten-15-25",
    "modifiedOn": "2023-12-15T11:44:14.4",
    "imageCount": 1,
    "presaleInfo": {
      "isPresale": false,
      "releasedOn": null,
      "note": null
    },
    "extendedData": [
      {
        "name": "Number",
        "displayName": "Card Number",
        "value": "015/025"
      },
      {
        "name": "Rarity",
        "displayName": "Rarity",
        "value": "Promo"
      },
      {
        "name": "Card Type",
        "displayName": "Card Type",
        "value": "Fire"
      },
      {
        "name": "HP",
        "displayName": "HP",
        "value": "70"
      },
      {
        "name": "Stage",
        "displayName": "Stage",
        "value": "Basic"
      },
      {
        "name": "Attack 1",
        "displayName": "Attack 1",
        "value": "[R] Bite (10)"
      },
      {
        "name": "Attack 2",
        "displayName": "Attack 2",
        "value": "[1R] Flare (20)"
      },
      {
        "name": "Weakness",
        "displayName": "Weakness",
        "value": "Wx2"
      },
      {
        "name": "RetreatCost",
        "displayName": "Retreat Cost",
        "value": "1"
      }
    ],
    "prices": [
      {
        "subTypeName": "Holofoil",
        "lowPrice": 0.32,
        "midPrice": 1,
        "highPrice": 7.29,
        "marketPrice": 0.88,
        "directLowPrice": 1.16
      },
      {
        "subTypeName": "Normal",
        "lowPrice": 0.05,
        "midPrice": 0.35,
        "highPrice": 2,
        "marketPrice": 0.3,
        "directLowPrice": null
      }
    ]
  },
  {
    "productId": 232748,
    "name": "McDonald's 25th Anniversary Booster Pack",
    "cleanName": "McDonalds 25th Anniversary Booster Pack",
    "imageUrl": "https://tcgplayer-cdn.tcgplayer.com/product/232748_200w.jpg",
    "categoryId": 3,
    "groupId": 2782,
    "url": "https://www.tcgplayer.com/product/232748/pokemon-mcdonalds-25th-anniversary-promos-mcdonalds-25th-anniversary-booster-pack",
    "modifiedOn": "2021-02-16T13:40:43.563",
    "imageCount": 1,
    "presaleInfo": {
      "isPresale": false,
      "releasedOn": null,
      "note": null
    },
    "extendedData": [
      {
        "name": "CardText",
        "displayName": "Card Text",
        "value": "Each McDonald's 25th Anniversary booster pack contains 4 promo cards."
      }
    ],
    "prices": [
      {
        "subTypeName": "Normal",
        "lowPrice": 2.99,
        "midPrice": 4.58,
        "highPrice": 35,
        "marketPrice": 3.98,
        "directLowPrice": null
      }
    ]
  }
]